Workbook

Sheet Dermatology
A1: (Do Not Modify) Provider Service | B1: (Do Not Modify) Row Checksum | C1: (Do Not Modify) Modified On | D1: Network Name | E1: Status | F1: VSS | G1: Availability | H1: Provider | I1: Notes (Provider) (Provider) | J1: Provider Identifier | K1: HPP | L1: Specialty | M1: Specialty Group (Specialty) (Specialty) | N1: Subservice Rollup | O1: Telehealth Available | P1: Care Site Phone Number | Q1: Care Site Fax (Caresite) (Care Site) | R1: Caresite | S1: Care Site Address | T1: Care Site City | U1: Care Site State | V1: Care Site Zip Code | W1: Organization / Group | X1: Created On | Y1: Deactivation Date | Z1: Coverage County | AA1: Catchment | AB1: HSRM | AC1: EPS | AD1: Compass_Display | AE1: Compass_Include | AF1: Compass_Office_Nickname | AG1: Compass_Referral_Fax | AH1: Compass_Medical_Records_Fax | AI1: Compass_Email | AJ1: Compass_HSRM_Status | AK1: Compass_EPS_Status | AL1: Compass_Accepting_Status | AM1: Compass_Preferred_Method | AN1: Compass_Internal_Notes | AO1: Compass_Referral_Comment_Notes | AP1: Compass_Tags | AQ1: Compass_Last_Verified | AR1: Compass_Verified_By | AS1: Compass_Update_Status | AT1: Compass_Update_Notes | AU1: Latitude | AV1: Longitude | AW1: Gecord_Status
A2: b5d793b2-7726-4425-ae68-3377951fbe2f | B2: Jy1sZRnl5gibAZT92a+pW7kHJy8O1VFRc0iOyBWi4sASY4d4du/teXgEc/Y1deY4GjwntIM5TZTI13uIiCegWA== | C2: 46152.198 | D2: CCN Region 2 | E2: Active | F2: No | G2: Accepting patients | H2: DERMATOLOGY SPEC OF GRAND RAPIDS PLLC | I2: No | J2: 1689306680 | K2: Unknown | L2: Dermatology | M2: Dermatology | O2: No | P2: 616-369-1600 | R2: DERMATOLOGY SPEC OF GRAND RAPIDS PLLC | S2: 1000 EAST PARIS AVE SE | T2: GRAND RAPIDS | U2: MI | V2: 49546-3691 | X2: 46152.031 | Z2: =_xlfn.XLOOKUP(VALUE(LEFT(V2,5)), 'MI Zip Codes'!A:A, 'MI Zip Codes'!B:B, "County Not Found") -> Kent | AA2: Battle Creek
A3: 6e280754-098f-41b3-beb7-9f29af42a2dd | B3: XA7mHnMZSQ8n3cqd9d39BIot/M5nWB0xbc3al+xQup7Kr3a12xYezpUGnipyaPD93LgT/a5ENSTSzTW5/3t0gA== | C3: 46169.613 | D3: CCN Region 2 | E3: Active | F3: No | G3: Accepting patients | H3: VISCONTI, MICHAEL | I3: No | J3: 1235767856 | K3: Unknown | L3: Dermatology | M3: Dermatology | O3: No | P3: 586-876-2345 | R3: DERMATOLOGY SPECIALISTS OF GRAND RAPIDS | S3: 1000 EAST PARIS AVE SE STE 104 | T3: GRAND RAPIDS | U3: MI | V3: 49546-3680 | W3: DERMATOLOGY SPECIALISTS OF GRAND RAPI | X3: 46169.446 | Z3: =_xlfn.XLOOKUP(VALUE(LEFT(V3,5)), 'MI Zip Codes'!A:A, 'MI Zip Codes'!B:B, "County Not Found") -> Kent | AA3: Battle Creek
A4: a00bf6c5-1987-4cb3-84a2-1057cd43edbc | B4: +iMknhY5w8iQp0WgTSZQTfC5M5eylIXFnmrhdcTT3SclrhGZ8Ncwz5ZMeQZUjoO3zNvMJ9OIPgSLJueZyw453A== | C4: 46010.322 | D4: CCN Region 2 | E4: Active | F4: No | G4: Accepting patients | H4: KOUBA, DAVID | I4: No | J4: 1073561866 | K4: Unknown | L4: Dermatology | M4: Dermatology | O4: No | R4: TOLEDO CLINIC DAVID KOUBA SOLE MBR | S4: 1136 COUNTRY CLUB RD UNIT C | T4: ADRIAN | U4: MI | V4: 49221-8209 | W4: TOLEDO CLINIC DAVID KOUBA SOLE MBR | X4: 45996.019 | Z4: =_xlfn.XLOOKUP(VALUE(LEFT(V4,5)), 'MI Zip Codes'!A:A, 'MI Zip Codes'!B:B, "County Not Found") -> Lenawee
A5: c957953d-ba9e-431c-b5a8-495aaf35800c | B5: jQ2Q9b/gaTvhToUkGyM5r1pVzNBwnBvPi7kR5jUwQUj0nfFmJw+oRAg+E0lj+C7WpnwlqyCEnKzTc5uSvhqLkg== | C5: 45899.865 | D5: CCN Region 2 | E5: Active | G5: Accepting patients | H5: KOUBA, DAVID | I5: No | J5: 1073561866 | K5: No | L5: Dermatology | M5: Dermatology | O5: No | P5: 517-366-5110 | Q5: 517-366-5115 | R5: TOLEDO CLINIC | S5: 1136 COUNTRY CLUB RD UNIT C | T5: ADRIAN | U5: MI | V5: 49221-8209 | W5: TOLEDO CLINIC | X5: 44884.404 | Z5: =_xlfn.XLOOKUP(VALUE(LEFT(V5,5)), 'MI Zip Codes'!A:A, 'MI Zip Codes'!B:B, "County Not Found") -> Lenawee
A6: 07944e46-e3f5-49cb-8497-0ee68f107c73 | B6: Ph0zmVuO6ijTATpU+g3CLDMgiowtySbxSH3U50JcXOW+wXqzD4cv0nl96/l/QRU0VNGAcU/P9qaxtT8fxvuOhg== | C6: 46019.279 | D6: CCN Region 2 | E6: Active | F6: No | G6: Accepting patients | H6: JAWORSKY, CHRISTINE | I6: No | J6: 1073592804 | K6: No | L6: Dermatology - Dermatopathology | M6: Dermatology | O6: No | P6: 419-534-3500 | Q6: 419-534-2608 | R6: CONSULTANTS IN LAB MEDTOLEDO | S6: 818 RIVERSIDE AVE | T6: ADRIAN | U6: MI | V6: 49221-1446 | W6: CONSULTANTS IN LAB MED TOLEDO | X6: 45415.012 | Z6: =_xlfn.XLOOKUP(VALUE(LEFT(V6,5)), 'MI Zip Codes'!A:A, 'MI Zip Codes'!B:B, "County Not Found") -> Lenawee
A7: 8e62484a-b763-45eb-b637-182147dd0ae0 | B7: Tzoy6Kd0EaERgCrlqQAwQs6yGUD/no8qdU5QkYkKkmHQWEASSNT7EZOYW8sEjAMN1fTd4e9XAf3jPJZFiMgeAg== | C7: 46051.882 | D7: CCN Region 2 | E7: Active | F7: No | G7: Accepting patients | H7: TOLEDO CLINIC | I7: No | J7: 1114079167 | K7: No | L7: Dermatology | M7: Dermatology | O7: No | P7: 517-366-5110 | Q7: 517-366-5115 | R7: TOLEDO CLINIC | S7: 1136 COUNTRY CLUB RD UNIT C | T7: ADRIAN | U7: MI | V7: 49221-8209 | X7: 45232.002 | Z7: =_xlfn.XLOOKUP(VALUE(LEFT(V7,5)), 'MI Zip Codes'!A:A, 'MI Zip Codes'!B:B, "County Not Found") -> Lenawee
A8: b5902d42-70dd-40ca-95c3-818e62fdf2b0 | B8: gWGad84sRpvJ7TsyeYpfwB4sqBrRMWnsB/PY04ukuqsG10jBhvG70YxzL2EvXYMU8ZunT9EItA3zexngVa5jNw== | C8: 46021.738 | D8: CCN Region 2 | E8: Active | G8: Accepting patients | H8: LAWRENCE J DESJARLAIS MD | I8: No | J8: 1306027073 | K8: No | L8: Dermatology | M8: Dermatology | P8: 517-264-5603 | Q8: 517-264-5708 | R8: LAWRENCE J DESJARLAIS MD | S8: 2000 CURTIS RD | T8: ADRIAN | U8: MI | V8: 49221-1778 | X8: 43854.335 | Z8: =_xlfn.XLOOKUP(VALUE(LEFT(V8,5)), 'MI Zip Codes'!A:A, 'MI Zip Codes'!B:B, "County Not Found") -> Lenawee
A9: 3a6a85b7-25af-4d75-ae50-2c689cdf9959 | B9: c9BbVj8axdB2u32jQnUMyw+k6HiUY4hXD1FzqLW8uDxUpettQDHhb2G6NTL4DISYC79VKMMypAsqoAWyoatZKg== | C9: 46000.691 | D9: CCN Region 2 | E9: Active | F9: No | G9: Accepting patients | H9: TOLEDO CLINIC DAVID KOUBA SOLE MBR | I9: No | J9: 1326538703 | K9: Unknown | L9: Dermatology | M9: Dermatology | O9: No | P9: 517-366-5110 | R9: TOLEDO CLINIC DAVID KOUBA SOLE MBR | S9: 1136 COUNTRY CLUB RD UNIT C | T9: ADRIAN | U9: MI | V9: 49221-8209 | X9: 45996.027 | Z9: =_xlfn.XLOOKUP(VALUE(LEFT(V9,5)), 'MI Zip Codes'!A:A, 'MI Zip Codes'!B:B, "County Not Found") -> Lenawee
A10: 0a9e3220-fcc8-488e-8384-401e3cd39cf3 | B10: mQUZMF2o3q9SE7bIDZXdyNyIgZE9BlRaSDkHguNX6JbqIDz56FE8tzkmYVYEbk1Rh0emKL84qiU/jRmorYmdwA== | C10: 46022.104 | D10: CCN Region 2 | E10: Active | G10: Accepting patients | H10: DESJARLAIS, LAWRENCE J | I10: No | J10: 1437116852 | K10: No | L10: Dermatology | M10: Dermatology | P10: 517-264-5603 | Q10: 517-264-5708 | R10: LAWRENCE J DESJARLAIS MD | S10: 2000 CURTIS RD | T10: ADRIAN | U10: MI | V10: 49221-1778 | W10: LAWRENCE J DESJARLAIS MD | X10: 43854.491 | Z10: =_xlfn.XLOOKUP(VALUE(LEFT(V10,5)), 'MI Zip Codes'!A:A, 'MI Zip Codes'!B:B, "County Not Found") -> Lenawee
A11: c297851a-aa3a-4b4e-95f1-d52c414df4b5 | B11: Y3h1SZk9UjFetFQ+Aw2+hRoJ/2UZdLjhYQEnY1hcwWcXAF7NlXCPMS39C/KYiYqtIw0kYoIEOaOy9BYcov0PRA== | C11: 46019.457 | D11: CCN Region 2 | E11: Active | F11: No | G11: Accepting patients | H11: ILYAS, MUNEEB | I11: No | J11: 1659876308 | K11: No | L11: Dermatology | M11: Dermatology | O11: No | P11: 419-473-3561 | R11: ADRIAN DERMASURGERY CENTER | S11: 1136 COUNTRY CLUB RD UNIT C | T11: ADRIAN | U11: MI | V11: 49221-8209 | W11: TOLEDO CLINIC DAVID KOUBA SOLE MBR | X11: 46010.09 | Z11: =_xlfn.XLOOKUP(VALUE(LEFT(V11,5)), 'MI Zip Codes'!A:A, 'MI Zip Codes'!B:B, "County Not Found") -> Lenawee
A12: c28076d1-8776-4e15-a746-a171d6cfee59 | B12: 9hOyvXdazTJdjfTMmyXc5725l28CZ5t9F+5y838qTnHtD6ExwaCuEmfIIWkQnoOSasgTqwF2KRMcW7urJi9qJQ== | C12: 46010.28 | D12: CCN Region 2 | E12: Active | F12: No | G12: Accepting patients | H12: TOLEDO CLINIC DAVID KOUBA SOLE MBR | I12: No | J12: 1700842796 | K12: Unknown | L12: Dermatology | M12: Dermatology | O12: No | P12: 419-473-3561 | R12: ADRIAN DERMASURGERY CENTER | S12: 1136 COUNTRY CLUB RD UNIT C | T12: ADRIAN | U12: MI | V12: 49221-8209 | X12: 46010.072 | Z12: =_xlfn.XLOOKUP(VALUE(LEFT(V12,5)), 'MI Zip Codes'!A:A, 'MI Zip Codes'!B:B, "County Not Found") -> Lenawee
A13: 6bd39877-9d24-4496-88cf-54bed4d36940 | B13: n1/IRVzRMyQslyqVoFGCRoHR1tBSmbD9udjjNB1UDCS1CA2dhPZiakfMcIkDtYp73zrjJu6tRP3SxLqOtGik3w== | C13: 45899.921 | D13: CCN Region 2 | E13: Active | F13: No | G13: Accepting patients | H13: WINFIELD, HARRY | I13: No | J13: 1922023670 | K13: Unknown | L13: Dermatology - Dermatopathology | M13: Dermatology | O13: No | P13: 419-534-3500 | Q13: 419-534-2608 | R13: CONSULTANTS IN LAB MEDTOLEDO | S13: 818 RIVERSIDE AVE | T13: ADRIAN | U13: MI | V13: 49221-1446 | W13: CONSULTANTS IN LAB MED TOLEDO | X13: 45415.013 | Z13: =_xlfn.XLOOKUP(VALUE(LEFT(V13,5)), 'MI Zip Codes'!A:A, 'MI Zip Codes'!B:B, "County Not Found") -> Lenawee
A14: 1ec3f9c1-0844-4bb6-8cd6-0dd0c7291bc6 | B14: KZbbQQR4Uu1vn+MK1yxBrD578zet3+Joxpiake7Hqc64G5cRAQhR+0tl0PnnlZVo2L1jSCpzrceedwxddjt69w== | C14: 45898.743 | D14: CCN Region 2 | E14: Active | F14: No | G14: Accepting patients | H14: CONSULTANTS IN LAB MED TOLEDO | I14: No | J14: 1982673372 | K14: Unknown | L14: Dermatology - Dermatopathology | M14: Dermatology | O14: No | P14: 419-534-3500 | Q14: 419-534-2608 | R14: CONSULTANTS IN LAB MEDTOLEDO | S14: 818 RIVERSIDE AVE | T14: ADRIAN | U14: MI | V14: 49221-1446 | X14: 45416.036 | Z14: =_xlfn.XLOOKUP(VALUE(LEFT(V14,5)), 'MI Zip Codes'!A:A, 'MI Zip Codes'!B:B, "County Not Found") -> Lenawee
A15: e7da7983-5e48-4352-a65e-fb9e96e78d2b | B15: bQt9ZkXFOixhqyw8u/RrjCfPRm4Z6uzDFzcbxVq0CeRebFkQXGfPnWGCtMvpzt/15rYNU0nUUu63o7h3Qt686g== | C15: 46169.612 | D15: CCN Region 2 | E15: Active | F15: No | G15: Accepting patients | H15: DERMATOLOGY SPECIALISTS OF GRAND RAPI | I15: No | J15: 1821972548 | K15: Unknown | L15: Dermatology | M15: Dermatology | O15: No | P15: 586-876-2345 | R15: DERMATOLOGY SPECIALISTS OF GRAND RAPIDS | S15: 1000 EAST PARIS AVE SE STE 104 | T15: GRAND RAPIDS | U15: MI | V15: 49546-3680 | X15: 46169.445 | Z15: =_xlfn.XLOOKUP(VALUE(LEFT(V15,5)), 'MI Zip Codes'!A:A, 'MI Zip Codes'!B:B, "County Not Found") -> Kent | AA15: Battle Creek
A16: e10343d3-0a5c-4f90-a632-8a3396330ba3 | B16: qr6dUvVbVMV3x0SSZ2A4JCZg4GFs1CqJLsaRJ2E6jF2G2oIw4YYKTgIsiwuEe/rtd525171GEYL32YEI6+5Z/g== | C16: 46094.228 | D16: CCN Region 2 | E16: Active | F16: No | G16: Accepting patients | H16: WMED HEALTH | I16: No | J16: 1316212343 | K16: No | L16: Dermatology | M16: Dermatology | O16: No | P16: 269-337-6500 | Q16: 269-337-6565 | R16: WESTERN MICHIGAN UNIVERSITY SCHOOL OF | S16: 1000 OAKLAND DR | T16: KALAMAZOO | U16: MI | V16: 49008-1282 | X16: 45213.718 | Z16: =_xlfn.XLOOKUP(VALUE(LEFT(V16,5)), 'MI Zip Codes'!A:A, 'MI Zip Codes'!B:B, "County Not Found") -> Kalamazoo | AA16: Battle Creek
A17: 9bff81a8-bd44-4de9-b188-68487dd923ee | B17: /O4Bh+ERK4ULEQ50fDanzMkqw3vGRmbD76Wr6kHP7BNOzsEYf7MYz+SkXwNwsdWyznk4UNwpsqAO3yQllfBq1Q== | C17: 45900.602 | D17: CCN Region 2 | E17: Active | G17: Accepting patients | H17: FOREFRONT DERMATOLOGY | I17: No | J17: 1003356692 | K17: Yes | L17: Dermatology | M17: Dermatology | O17: No | P17: 616-459-7122 | R17: FOREFRONT DERMATOLOGY | S17: 1005 W GREEN ST STE 200 | T17: HASTINGS | U17: MI | V17: 49058-1726 | X17: 44059.698 | Z17: =_xlfn.XLOOKUP(VALUE(LEFT(V17,5)), 'MI Zip Codes'!A:A, 'MI Zip Codes'!B:B, "County Not Found") -> Barry | AA17: Battle Creek
A18: 79c27c74-a395-4704-b04e-2aa7788920cd | B18: IZvtrS6+MhcdYWYQiq5lUwoSeinh545goFpUQcAaOi5h0Q8CPO/oqL99pJNZ6IP1ru4ix9y2qnySfcUbB5xDvA== | C18: 45899.653 | D18: CCN Region 2 | E18: Active | G18: Accepting patients | H18: MESSING, ROBYN | I18: No | J18: 1215019682 | K18: No | L18: Dermatology | M18: Dermatology | O18: No | P18: 517-627-2181 | Q18: 517-622-1242 | R18: FAMILY MEDICINE OF MICHIGAN | S18: 1035 CHARLEVOIX DR STE 100 | T18: GRAND LEDGE | U18: MI | V18: 48837-2223 | W18: SMITH | X18: 44162.061 | Z18: =_xlfn.XLOOKUP(VALUE(LEFT(V18,5)), 'MI Zip Codes'!A:A, 'MI Zip Codes'!B:B, "County Not Found") -> Eaton | AA18: Battle Creek
A19: 26cdefea-fff4-4e55-b5c2-3ddd945a07a8 | B19: N1OhtLXApEVB053Jp0DYbRMLSaOBi65okBQ8M431ZZ629ohwZPdJbs9VDK4h0yYCEYFOQc1r3wB+mPTpFGnMiA== | C19: 46030.554 | D19: CCN Region 2 | E19: Active | G19: Accepting patients | H19: COTTER, MURRAY | I19: No | J19: 1669598744 | K19: No | L19: Dermatology | M19: Dermatology | P19: 989-884-0139 | Q19: 989-356-6396 | R19: ADVANCED DERMATOLOGY OF MICHIGAN | S19: 105 ARBOR LN | T19: ALPENA | U19: MI | V19: 49707-1301 | W19: ADVANCED DERMATOLOGY OF MICHIGAN | X19: 43971.044 | Z19: =_xlfn.XLOOKUP(VALUE(LEFT(V19,5)), 'MI Zip Codes'!A:A, 'MI Zip Codes'!B:B, "County Not Found") -> Alpena
A20: 51555f60-735a-422f-8b63-205cb2d938e9 | B20: tjT2lmLFkiU9P7tgBd3Wi+JjsNOlHf1jN0xlYGGDz6RyeJZ+PO4bD8e5Rluck2AUSGykMTYeUYVaoN8HFXrAQg== | C20: 45898.806 | D20: CCN Region 2 | E20: Active | G20: Accepting patients | H20: ADVANCED DERMATOLOGY OF MICHIGAN | I20: No | J20: 1851708929 | K20: Unknown | L20: Dermatology | M20: Dermatology | P20: 989-884-0139 | Q20: 989-356-6396 | R20: ADVANCED DERMATOLOGY OF MICHIGAN | S20: 105 ARBOR LN | T20: ALPENA | U20: MI | V20: 49707-1301 | X20: 43915.38 | Z20: =_xlfn.XLOOKUP(VALUE(LEFT(V20,5)), 'MI Zip Codes'!A:A, 'MI Zip Codes'!B:B, "County Not Found") -> Alpena
A21: 00d2dd38-ddb3-4a71-9165-ea17790b75a3 | B21: zpBvjKD9VppI6bepw1Pj7dV5jiSNQshdEUh16E+WoeZ7U4bF3qAA9wVJKUB6YA92NWLMGXJBsXSsMNPy5+OE4Q== | C21: 45902.537 | D21: CCN Region 2 | E21: Active | G21: Accepting patients | H21: ADVANCED DERMATOLOGY OF MICHIGAN | I21: No | J21: 1851708929 | K21: Unknown | L21: Dermatology | M21: Dermatology | P21: 989-884-0139 | Q21: 989-356-6396 | R21: ADVANCED DERMATOLOGY OF MICHIGAN | S21: 105 ARBOR LANE | T21: ALPENA | U21: MI | V21: 49707-1301 | X21: 43915.38 | Z21: =_xlfn.XLOOKUP(VALUE(LEFT(V21,5)), 'MI Zip Codes'!A:A, 'MI Zip Codes'!B:B, "County Not Found") -> Alpena
A22: 06cfae30-68d3-4968-82da-2baa35ef224f | B22: nqQXGmLxmkkUyc5ztU9l1CmLjCL+j7T9HJTfHI96TYASZGx6hcKb9jQNBK1AvfV7TiMLwuDJDUNp0lzPzT7nKg== | C22: 45899.654 | D22: CCN Region 2 | E22: Active | F22: No | G22: Accepting patients | H22: REGENTS OF UNIVERSITY OF MICH | I22: No | J22: 1003848144 | K22: Unknown | L22: Dermatology - MOHS-Micrographic Surgery | M22: Dermatology | O22: No | P22: 734-936-4054 | Q22: 734-647-6593 | R22: REGENTS OF UNIVERSITY OF MICH | S22: 1500 E MED CTR DR FL B1 TAUBMAN | T22: ANN ARBOR | U22: MI | V22: 48109 | X22: 45241.161 | Z22: =_xlfn.XLOOKUP(VALUE(LEFT(V22,5)), 'MI Zip Codes'!A:A, 'MI Zip Codes'!B:B, "County Not Found") -> Washtenaw
A23: ccd6de6e-5524-42a0-92ec-7d2f547ec2fc | B23: pPJSQW/VMckDSsRj5quY7TSeDpwZo2OLiQSi/mNqtzIqPUhB0B5t2utJJKnC+JoM2a0WvdJUAXZoHdxnPt72dg== | C23: 45900.65 | D23: CCN Region 2 | E23: Active | F23: No | G23: Accepting patients | H23: REGENTS OF UNIVERSITY OF MICH | I23: No | J23: 1003848144 | K23: Unknown | L23: Dermatology - Procedural Dermatology | M23: Dermatology | O23: No | P23: 734-936-4054 | Q23: 734-647-6593 | R23: REGENTS OF UNIVERSITY OF MICH | S23: 1500 E MED CTR DR FL B1 TAUBMAN | T23: ANN ARBOR | U23: MI | V23: 48109 | X23: 45241.161 | Z23: =_xlfn.XLOOKUP(VALUE(LEFT(V23,5)), 'MI Zip Codes'!A:A, 'MI Zip Codes'!B:B, "County Not Found") -> Washtenaw
A24: 9ba974a3-d3c2-424f-a84c-f727506e67a4 | B24: D5APO8E3Od8uTyvQ1Kk0bao//XzrCKCheq5WOPyRSOl/SAG8s/N8WzQICVCbVvbFj2VpSGNxHIOoxifXA2zpdA== | C24: 45902.601 | D24: CCN Region 2 | E24: Active | F24: No | G24: Accepting patients | H24: REGENTS OF UNIVERSITY OF MICH | I24: No | J24: 1003848144 | K24: Unknown | L24: Dermatology | M24: Dermatology | O24: No | P24: 734-936-4054 | Q24: 734-647-6593 | R24: REGENTS OF UNIVERSITY OF MICH | S24: 1500 E MED CTR DR FL B1 TAUBMAN | T24: ANN ARBOR | U24: MI | V24: 48109 | X24: 45241.161 | Z24: =_xlfn.XLOOKUP(VALUE(LEFT(V24,5)), 'MI Zip Codes'!A:A, 'MI Zip Codes'!B:B, "County Not Found") -> Washtenaw
A25: 06fb75d4-6a9b-4c56-85c4-42c9de7db75f | B25: lD9Qw/kLqxjJpllUPj+tj1T5tNLpbdrWObf3lqYO663Sm5KkJDslyI5AZQY2o+XSE3LI/MttdS5x6cX7EaFddQ== | C25: 46194.183 | D25: CCN Region 2 | E25: Active | G25: Accepting patients | H25: RAMIREZ, JAMES | I25: No | J25: 1003867946 | K25: No | L25: Pathology - Dermatopathology | M25: Dermatology | O25: No | P25: 248-360-5881 | R25: ST JOSEPH MERCY HOSPITAL | S25: 5301 E HURON RIVER DR | T25: ANN ARBOR | U25: MI | V25: 48106 | W25: ST JOSEPH MERCY HOSPITAL | X25: 44072.193 | Z25: =_xlfn.XLOOKUP(VALUE(LEFT(V25,5)), 'MI Zip Codes'!A:A, 'MI Zip Codes'!B:B, "County Not Found") -> Washtenaw
A26: a58fe9e1-2bdd-4e94-8586-026c58e58207 | B26: b1WBuMoErNuOMVvfztZFkeQgXduDPiBYs3YsC9VrfRTIj1Na+zb7DpipgMF2sd6M7cFWaIgO7kyhYplw28qRGw== | C26: 46182.68 | D26: CCN Region 2 | E26: Active | F26: No | G26: Accepting patients | H26: REGENTS OF THE UNIVERSITY OF MICHIGAN | I26: Yes | J26: 1003878539 | K26: Unknown | L26: Dermatology | M26: Dermatology | O26: No | P26: 734-936-4054 | Q26: 734-647-6593 | R26: REGENTS OF UNIVERSITY OF MICH | S26: 1500 E MEDICAL CENTER DR FL 1 | T26: ANN ARBOR | U26: MI | V26: 48109-5000 | X26: 45543.071 | Z26: =_xlfn.XLOOKUP(VALUE(LEFT(V26,5)), 'MI Zip Codes'!A:A, 'MI Zip Codes'!B:B, "County Not Found") -> Washtenaw
A27: 91134781-62ad-4a67-88a4-1f37b31801bd | B27: 8BaS5BTl20o13vyPHIz5sGjnqg96AmdmDrcsPWeGIVZuK9FuoIWtNvvjf4dyS0D8kdx5cpEUCzVcsTzvUbelnQ== | C27: 46182.68 | D27: CCN Region 2 | E27: Active | F27: No | G27: Accepting patients | H27: REGENTS OF THE UNIVERSITY OF MICHIGAN | I27: Yes | J27: 1003878539 | K27: Unknown | L27: Dermatology - Procedural Dermatology | M27: Dermatology | O27: No | P27: 734-936-4054 | R27: REGENTS OF UNIVERSITY OF MICH | S27: 1500 E MED CTR DR FL 1 RECP B | T27: ANN ARBOR | U27: MI | V27: 48109 | X27: 45858.02 | Z27: =_xlfn.XLOOKUP(VALUE(LEFT(V27,5)), 'MI Zip Codes'!A:A, 'MI Zip Codes'!B:B, "County Not Found") -> Washtenaw
A28: 19201116-84b6-489e-9941-2f223a62fd3d | B28: 2DfVp9r++7Csxd4FBgxrq9aNXHQjiXSJBd+W4qXdN0BdBzIk3FSZsaA4kL5Y0uWZZltls5ERq+mkvivNmpejuQ== | C28: 46182.68 | D28: CCN Region 2 | E28: Active | F28: No | G28: Accepting patients | H28: REGENTS OF THE UNIVERSITY OF MICHIGAN | I28: Yes | J28: 1003878539 | K28: Unknown | L28: Dermatology - Procedural Dermatology | M28: Dermatology | O28: No | P28: 734-936-6000 | R28: REGENTS OF UNIVERSITY OF MICH | S28: 1500 E MEDICAL CENTER DR FL 1 CANCER CTR | T28: ANN ARBOR | U28: MI | V28: 48109-5000 | X28: 45543.07 | Z28: =_xlfn.XLOOKUP(VALUE(LEFT(V28,5)), 'MI Zip Codes'!A:A, 'MI Zip Codes'!B:B, "County Not Found") -> Washtenaw
A29: 136948c7-dd3e-440a-b4b3-5a6b659a9430 | B29: yj1hMPydwW8bLKO42dmUbcjXtC+jjiTP8obcpV2kS13Hk1ALbBM/bs2Tc6GQQBw14HzRKwtPwA1ApYLjbCS3Uw== | C29: 46182.68 | D29: CCN Region 2 | E29: Active | F29: No | G29: Accepting patients | H29: REGENTS OF THE UNIVERSITY OF MICHIGAN | I29: Yes | J29: 1003878539 | K29: Unknown | L29: Dermatology - MOHS-Micrographic Surgery | M29: Dermatology | O29: No | P29: 734-936-6000 | R29: REGENTS OF UNIVERSITY OF MICH | S29: 1500 E MEDICAL CENTER DR FL 1 CANCER CTR | T29: ANN ARBOR | U29: MI | V29: 48109-5000 | X29: 45543.07 | Z29: =_xlfn.XLOOKUP(VALUE(LEFT(V29,5)), 'MI Zip Codes'!A:A, 'MI Zip Codes'!B:B, "County Not Found") -> Washtenaw
A30: 7b3e841b-07d0-4992-b35a-620e3a9a9d2c | B30: hxAkPZBnL0am9U1qWk/tBV1SOOu0fqE6jYErIgKTnk1n3vFWSL8aWWlsKFO8yDctMX4BRrW8aMpmdLHkQ9KdBQ== | C30: 46182.68 | D30: CCN Region 2 | E30: Active | F30: No | G30: Accepting patients | H30: REGENTS OF THE UNIVERSITY OF MICHIGAN | I30: Yes | J30: 1003878539 | K30: Unknown | L30: Dermatology | M30: Dermatology | O30: No | P30: 734-936-4054 | R30: REGENTS OF UNIVERSITY OF MICH | S30: 24 FRANK LLOYD WRIGHT DR # H2350 | T30: ANN ARBOR | U30: MI | V30: 48105-9484 | X30: 45543.071 | Z30: =_xlfn.XLOOKUP(VALUE(LEFT(V30,5)), 'MI Zip Codes'!A:A, 'MI Zip Codes'!B:B, "County Not Found") -> Washtenaw
A31: 82898a99-9305-4fbf-9780-6b8d04d426d9 | B31: DuwZPCKBfOOBMgYgA1aKIahhEhOzVPI3pe79mo5Wwd8T3qc+tFD57+ITqls56P4LgFg3RvmW90M+x4QFXbLFwg== | C31: 46182.68 | D31: CCN Region 2 | E31: Active | F31: No | G31: Accepting patients | H31: REGENTS OF THE UNIVERSITY OF MICHIGAN | I31: Yes | J31: 1003878539 | K31: Unknown | L31: Dermatology - MOHS-Micrographic Surgery | M31: Dermatology | O31: No | P31: 734-936-4054 | R31: REGENTS OF UNIVERSITY OF MICH | S31: 1500 E MED CTR DR FL 1 RECP B | T31: ANN ARBOR | U31: MI | V31: 48109 | X31: 45858.02 | Z31: =_xlfn.XLOOKUP(VALUE(LEFT(V31,5)), 'MI Zip Codes'!A:A, 'MI Zip Codes'!B:B, "County Not Found") -> Washtenaw
A32: 84ebf9dd-08d6-4f2e-8512-7c7b941e8cab | B32: KznFVNe7+yEQ4JkZQkGHCuPmEPCFD575iIFUNWxJYgLzcDFjsax3MZbF8RTr73cik5D35lKsRUz2JrgeO2VL5Q== | C32: 46182.68 | D32: CCN Region 2 | E32: Active | F32: No | G32: Accepting patients | H32: REGENTS OF THE UNIVERSITY OF MICHIGAN | I32: Yes | J32: 1003878539 | K32: Unknown | L32: Dermatology | M32: Dermatology | O32: No | P32: 734-936-6000 | R32: REGENTS OF UNIVERSITY OF MICH | S32: 1500 E MEDICAL CENTER DR FL 1 CANCER CTR | T32: ANN ARBOR | U32: MI | V32: 48109-5000 | X32: 45543.07 | Z32: =_xlfn.XLOOKUP(VALUE(LEFT(V32,5)), 'MI Zip Codes'!A:A, 'MI Zip Codes'!B:B, "County Not Found") -> Washtenaw
A33: e9e99985-7329-44c7-b5b9-845e7b83596a | B33: GASWHVZAJGIjCoj9RLw7A9swjps18r5EmO/UiQ+JFgVoB0Ux0ZSsL1JnqFCga1OqyA+Xl2A39IAg69sB+HFw5g== | C33: 46182.68 | D33: CCN Region 2 | E33: Active | F33: No | G33: Accepting patients | H33: REGENTS OF THE UNIVERSITY OF MICHIGAN | I33: Yes | J33: 1003878539 | K33: Unknown | L33: Dermatology | M33: Dermatology | O33: No | P33: 734-936-4054 | R33: REGENTS OF UNIVERSITY OF MICH | S33: 1500 E MED CTR DR 8TH FL CS MOTT | T33: ANN ARBOR | U33: MI | V33: 48109 | X33: 45543.07 | Z33: =_xlfn.XLOOKUP(VALUE(LEFT(V33,5)), 'MI Zip Codes'!A:A, 'MI Zip Codes'!B:B, "County Not Found") -> Washtenaw
A34: 6179cdcd-f147-43bf-801f-8fefefa88c36 | B34: /t1c9YZU+uvNJ8dpkoJ6YclGSLNQjYzqXGjGh/rU1u8n+O5qGHg6dfgMIjMsx4IbWcS5nyV//buTSObQE4RE+w== | C34: 46182.68 | D34: CCN Region 2 | E34: Active | F34: No | G34: Accepting patients | H34: REGENTS OF THE UNIVERSITY OF MICHIGAN | I34: Yes | J34: 1003878539 | K34: Unknown | L34: Dermatology | M34: Dermatology | O34: No | P34: 734-936-5900 | R34: REGENTS OF UNIVERSITY OF MICH | S34: 1500 E MEDICAL CENTER DR FL B1 | T34: ANN ARBOR | U34: MI | V34: 48109-5000 | X34: 45543.071 | Z34: =_xlfn.XLOOKUP(VALUE(LEFT(V34,5)), 'MI Zip Codes'!A:A, 'MI Zip Codes'!B:B, "County Not Found") -> Washtenaw
A35: dfabc2c9-4e3e-48f0-8f8e-aa89234fd926 | B35: VRMtBN+cwijDegrpqE4Ak+zl3RJ3zpsRITVqUsQVT9xSAZWr2tyCGK9oLRdWg4xSAELuO49bHaQilYMdaDruiA== | C35: 46182.68 | D35: CCN Region 2 | E35: Active | F35: No | G35: Accepting patients | H35: REGENTS OF THE UNIVERSITY OF MICHIGAN | I35: Yes | J35: 1003878539 | K35: Unknown | L35: Dermatology | M35: Dermatology | O35: No | P35: 734-936-4054 | R35: REGENTS OF UNIVERSITY OF MICH | S35: 1500 E MED CTR DR FL 1 RECP B | T35: ANN ARBOR | U35: MI | V35: 48109 | X35: 45858.02 | Z35: =_xlfn.XLOOKUP(VALUE(LEFT(V35,5)), 'MI Zip Codes'!A:A, 'MI Zip Codes'!B:B, "County Not Found") -> Washtenaw
A36: a93013b7-7e93-432e-9f5c-b00ae45cbf67 | B36: cO/4vwPKnzK9lXlhEge1rYPWJl20Ibgz9a/q8TsFni/xbA2TkAp1cqz61GNC9ncqAYGFlRepaffCcoVpvJASSQ== | C36: 46182.68 | D36: CCN Region 2 | E36: Active | F36: No | G36: Accepting patients | H36: REGENTS OF THE UNIVERSITY OF MICHIGAN | I36: Yes | J36: 1003878539 | K36: Unknown | L36: Dermatology | M36: Dermatology | O36: No | P36: 734-936-4054 | R36: REGENTS OF UNIVERSITY OF MICH | S36: 24 FRANK LLOYD WRIGHT DR # 2350 | T36: ANN ARBOR | U36: MI | V36: 48105-9484 | X36: 45543.07 | Z36: =_xlfn.XLOOKUP(VALUE(LEFT(V36,5)), 'MI Zip Codes'!A:A, 'MI Zip Codes'!B:B, "County Not Found") -> Washtenaw
A37: e6b8686e-6220-4957-b07b-b8e053ff272f | B37: t+6DDDkNVSM21FfjwtE6NfPu5I6GaEmJVi0G3bXLPrYp9ws4pXSkuaTegv+38pb/Zr0CY4yS6OoOWE80oJdWPw== | C37: 46182.68 | D37: CCN Region 2 | E37: Active | F37: No | G37: Accepting patients | H37: REGENTS OF THE UNIVERSITY OF MICHIGAN | I37: Yes | J37: 1003878539 | K37: Unknown | L37: Dermatology | M37: Dermatology | O37: No | P37: 734-936-4054 | R37: REGENTS OF UNIVERSITY OF MICH | S37: 24 FRANK LLOYD WRIGHT DR # H2300 | T37: ANN ARBOR | U37: MI | V37: 48105-9484 | X37: 45543.071 | Z37: =_xlfn.XLOOKUP(VALUE(LEFT(V37,5)), 'MI Zip Codes'!A:A, 'MI Zip Codes'!B:B, "County Not Found") -> Washtenaw
A38: 5d05d982-1250-45ff-9d70-d7e6fe11bdce | B38: 1sAz1AtvNj14/9zrmxhC62Wm6TqYIGMkMi9BlDrIGzd5Jhq22kKUvqjoBVUmSIeCNP5lT9IkOIbpdmLf6k6mjw== | C38: 46182.68 | D38: CCN Region 2 | E38: Active | F38: No | G38: Accepting patients | H38: REGENTS OF THE UNIVERSITY OF MICHIGAN | I38: Yes | J38: 1003878539 | K38: Unknown | L38: Dermatology | M38: Dermatology | O38: No | P38: 734-763-9142 | R38: REGENTS OF UNIVERSITY OF MICH | S38: 1500 E MED CTR FL B1 TAUBMAN | T38: ANN ARBOR | U38: MI | V38: 48109 | X38: 45543.07 | Z38: =_xlfn.XLOOKUP(VALUE(LEFT(V38,5)), 'MI Zip Codes'!A:A, 'MI Zip Codes'!B:B, "County Not Found") -> Washtenaw
A39: 6895d054-e33f-48f0-87eb-1c2aa434f626 | B39: Txz84Mk13fBXWq9VItk29Bq+HmuieWdscJZTmNqkS4zJnLQPNwf0tyz2SrJ218GUY7YR6ZuN52Z25E7c9TVPww== | C39: 45898.793 | D39: CCN Region 2 | E39: Active | G39: Accepting patients | H39: HELFRICH, YOLANDA | I39: No | J39: 1003903873 | K39: Unknown | L39: Dermatology | M39: Dermatology | O39: No | P39: 734-998-7400 | R39: REGENTS OF UNIVERSITY OF MICH | S39: 24 FRANK LLOYD WRIGHT DR | T39: ANN ARBOR | U39: MI | V39: 48105-9484 | W39: REGENTS OF UNIV OF MICH | X39: 44364.015 | Z39: =_xlfn.XLOOKUP(VALUE(LEFT(V39,5)), 'MI Zip Codes'!A:A, 'MI Zip Codes'!B:B, "County Not Found") -> Washtenaw
A40: 37e10387-e980-4f1e-9fe7-205dad94b992 | B40: U2rlREHwyao6nZgtkQ85kso+57xaTPVUGxPZwLfZJ3+f8r0J0hQG7/KkL5Njk1EAQsDnU8l85YTukfctPXDk/Q== | C40: 46113.192 | D40: CCN Region 2 | E40: Active | G40: Accepting patients | H40: HELFRICH, YOLANDA | I40: No | J40: 1003903873 | K40: No | L40: Dermatology | M40: Dermatology | O40: No | P40: 734-998-7400 | R40: REGENTS OF UNIVERSITY OF MICH | S40: 24 FRANK LLOYD WRIGHT DR | T40: ANN ARBOR | U40: MI | V40: 48105-9484 | W40: REGENTS OF UNIVERSITY OF MICH | X40: 44405.217 | Z40: =_xlfn.XLOOKUP(VALUE(LEFT(V40,5)), 'MI Zip Codes'!A:A, 'MI Zip Codes'!B:B, "County Not Found") -> Washtenaw
A41: ed0c2216-f53d-4892-a523-26b476084ea8 | B41: D8Ch2UXsCOWNYraw3sRdkdI0C9N9J6MllLQMvKquNvTw2FedtcsjVS94EhzzDscxcw96uzxi/fmACtKAlTg3lQ== | C41: 45899.643 | D41: CCN Region 2 | E41: Active | G41: Accepting patients | H41: HELFRICH, YOLANDA | I41: No | J41: 1003903873 | K41: Unknown | L41: Dermatology | M41: Dermatology | O41: No | P41: 734-936-8000 | Q41: 734-936-9294 | R41: REGENTS OF UNIVERSITY OF MICH | S41: 1500 E MEDICAL CENTER DR | T41: ANN ARBOR | U41: MI | V41: 48109-5000 | W41: REGENTS OF THE UNIVERSITY OF MICHIGAN | X41: 43998.22 | Z41: =_xlfn.XLOOKUP(VALUE(LEFT(V41,5)), 'MI Zip Codes'!A:A, 'MI Zip Codes'!B:B, "County Not Found") -> Washtenaw
A42: b4092497-476b-4e15-9a1e-2a05e9471efb | B42: XbFLGABHg+8KIROsIFtOeM2ovPBoeuYycI6t2xwlbty9L5Wtr4n3WB35FHbDQ+Pa4meaykz6+7pn4G5bhXo/GQ== | C42: 45899.653 | D42: CCN Region 2 | E42: Active | G42: Accepting patients | H42: HELFRICH, YOLANDA | I42: No | J42: 1003903873 | K42: No | L42: Dermatology | M42: Dermatology | O42: No | P42: 734-763-4109 | R42: REGENTS OF UNIVERSITY OF MICH | S42: 1500 E MEDICAL CENTER DR 8TH FL | T42: ANN ARBOR | U42: MI | V42: 48109-5000 | W42: REGENTS OF UNIVERSITY OF MICH | X42: 44115.979 | Z42: =_xlfn.XLOOKUP(VALUE(LEFT(V42,5)), 'MI Zip Codes'!A:A, 'MI Zip Codes'!B:B, "County Not Found") -> Washtenaw
A43: 3b96ccd1-fc80-49ba-867f-3081d1bd5bba | B43: tEzN+dQdhrWVEbI6WFLhlgi7E1vYMIMAcVmDplP3q8YXpPIglxjWSGgDQdgAszqgmARYPbMSksVwiIXyrbQw9g== | C43: 45899.66 | D43: CCN Region 2 | E43: Active | G43: Accepting patients | H43: HELFRICH, YOLANDA | I43: No | J43: 1003903873 | K43: Unknown | L43: Dermatology | M43: Dermatology | O43: No | P43: 734-936-8000 | Q43: 734-936-9294 | R43: REGENTS OF UNIVERSITY OF MICH | S43: 1500 E MEDICAL CENTER DR | T43: ANN ARBOR | U43: MI | V43: 48109-5000 | W43: REGENTS OF UNIVERSITY OF MICH | X43: 44107.986 | Z43: =_xlfn.XLOOKUP(VALUE(LEFT(V43,5)), 'MI Zip Codes'!A:A, 'MI Zip Codes'!B:B, "County Not Found") -> Washtenaw
A44: b00e3f03-f038-46d2-9379-4819dcab65da | B44: oALp9KDSLf60DZs1bUd5rz5AEC10IQpLnI0VWdYi7zBtAuei1aDeV4YSHQG0/GVXf0nxpoUPSttYdlpfoXYOnw== | C44: 45899.865 | D44: CCN Region 2 | E44: Active | G44: Accepting patients | H44: HELFRICH, YOLANDA | I44: No | J44: 1003903873 | K44: Unknown | L44: Dermatology | M44: Dermatology | O44: No | P44: 734-936-8000 | R44: REGENTS OF UNIVERSITY OF MICH | S44: 1500 E MEDICAL CENTER DR | T44: ANN ARBOR | U44: MI | V44: 48109-5000 | W44: REGENTS OF UNIVERSITY OF MICH | X44: 44465.507 | Z44: =_xlfn.XLOOKUP(VALUE(LEFT(V44,5)), 'MI Zip Codes'!A:A, 'MI Zip Codes'!B:B, "County Not Found") -> Washtenaw
A45: 80227076-1771-4fd4-81e7-602cec66f122 | B45: 4WsHIkQzA/Q9hmL9QI9rnnicWCBI0YsOEvnW1iy4nZI7pj7xOUSayMzQsDt04UBhbZwpPzG25UuHzTKfjmpfCA== | C45: 45899.934 | D45: CCN Region 2 | E45: Active | G45: Accepting patients | H45: HELFRICH, YOLANDA | I45: No | J45: 1003903873 | K45: Unknown | L45: Dermatology | M45: Dermatology | O45: No | P45: 734-763-4109 | R45: REGENTS OF UNIVERSITY OF MICH | S45: 1500 E MEDICAL CENTER DR | T45: ANN ARBOR | U45: MI | V45: 48109-5000 | W45: REGENTS OF UNIVERSITY OF MICH | X45: 43997.257 | Z45: =_xlfn.XLOOKUP(VALUE(LEFT(V45,5)), 'MI Zip Codes'!A:A, 'MI Zip Codes'!B:B, "County Not Found") -> Washtenaw
A46: 7be33a30-2918-4f94-a22d-9aa3c0fdf30a | B46: KJ89IaraUfRcV9KjRPnFke+PgYIeYIn6q8XvMefZOX063/EHJG5g6Jupk/c1annczwgr9AgEgX1khn73a3WE3A== | C46: 45901.549 | D46: CCN Region 2 | E46: Active | G46: Accepting patients | H46: HELFRICH, YOLANDA | I46: No | J46: 1003903873 | K46: Unknown | L46: Dermatology | M46: Dermatology | O46: No | P46: 734-763-4109 | R46: REGENTS OF UNIVERSITY OF MICH | S46: 1500 E MEDICAL CENTER DR | T46: ANN ARBOR | U46: MI | V46: 48109-5000 | W46: REGENTS OF UNIVERSITY OF MICH | X46: 44069.163 | Z46: =_xlfn.XLOOKUP(VALUE(LEFT(V46,5)), 'MI Zip Codes'!A:A, 'MI Zip Codes'!B:B, "County Not Found") -> Washtenaw
A47: 292f154c-9d5a-4f8f-89f3-b2d12e2affc1 | B47: dmnlLBV+FAbz6u98ECHY4kYpr4JTkJKj+bXedfY29woMJgReGwaHBvy3dOdiFeOzBNnPzJtQW5nM5GpkuVmrZA== | C47: 45901.596 | D47: CCN Region 2 | E47: Active | G47: Accepting patients | H47: HELFRICH, YOLANDA | I47: No | J47: 1003903873 | K47: Unknown | L47: Dermatology | M47: Dermatology | P47: 734-998-7400 | R47: REGENTS OF UNIVERSITY OF MICH | S47: 24 FRANK LLOYD WRIGHT DR | T47: ANN ARBOR | U47: MI | V47: 48105-9484 | W47: REGENTS OF THE UNIVERSITY OF MICHIGAN | X47: 43915.412 | Z47: =_xlfn.XLOOKUP(VALUE(LEFT(V47,5)), 'MI Zip Codes'!A:A, 'MI Zip Codes'!B:B, "County Not Found") -> Washtenaw
A48: 263ffe5d-b0b3-4d0d-b330-c44135863544 | B48: VfYsOH6A2wVsVIyACoYIHHAFKMOG+syChjjMU13Z7zyLTktxWfUwMlcguzerxWJbbXkibn6jSYa0UTH5nh3rXA== | C48: 45901.703 | D48: CCN Region 2 | E48: Active | G48: Accepting patients | H48: HELFRICH, YOLANDA | I48: No | J48: 1003903873 | K48: Unknown | L48: Dermatology | M48: Dermatology | O48: No | P48: 734-936-8000 | R48: REGENTS OF UNIVERSITY OF MICH | S48: 1500 E MEDICAL CENTER DR | T48: ANN ARBOR | U48: MI | V48: 48109-5000 | W48: REGENTS OF UNIVERSITY OF MICH | X48: 44048.153 | Z48: =_xlfn.XLOOKUP(VALUE(LEFT(V48,5)), 'MI Zip Codes'!A:A, 'MI Zip Codes'!B:B, "County Not Found") -> Washtenaw
A49: 66af9cf0-f168-46bc-96dc-e41408cebd90 | B49: Vx12Q/lgHWdWj2/Xgxnf/8CXa4iKCUGYuoyMMLV2HrUGJEFJKnzcac8rTihdloTMA4lNDr788gDlet8EQ6Ayjg== | C49: 45902.523 | D49: CCN Region 2 | E49: Active | G49: Accepting patients | H49: HELFRICH, YOLANDA | I49: No | J49: 1003903873 | K49: No | L49: Dermatology | M49: Dermatology | P49: 734-936-4054 | R49: REGENTS OF UNIVERSITY OF MICH | S49: 24 FRANK LLOYD WRIGHT DR # H2350 | T49: ANN ARBOR | U49: MI | V49: 48105-9484 | W49: REGENTS OF THE UNIVERSITY OF MICHIGAN | X49: 43915.412 | Z49: =_xlfn.XLOOKUP(VALUE(LEFT(V49,5)), 'MI Zip Codes'!A:A, 'MI Zip Codes'!B:B, "County Not Found") -> Washtenaw
A50: 2bc9b8fe-6646-468d-85aa-e6d7f7995035 | B50: o0iNnnMFlFcgUONC07qiqqy5ewNojfyT+KIctVElVGgUTbpqmU3t9hkZp8YQRUhsIaHscAvH7j/5A+Zo6Pf8wQ== | C50: 45902.53 | D50: CCN Region 2 | E50: Active | G50: Accepting patients | H50: HELFRICH, YOLANDA | I50: No | J50: 1003903873 | K50: Unknown | L50: Dermatology | M50: Dermatology | O50: No | P50: 734-936-8000 | R50: REGENTS OF UNIVERSITY OF MICH | S50: 1500 E MEDICAL CENTER DR | T50: ANN ARBOR | U50: MI | V50: 48109-5000 | W50: REGENTS OF UNIVERSITY OF MICH | X50: 44619.087 | Z50: =_xlfn.XLOOKUP(VALUE(LEFT(V50,5)), 'MI Zip Codes'!A:A, 'MI Zip Codes'!B:B, "County Not Found") -> Washtenaw
A51: 7d33fea0-0f11-41ed-9ba1-ecd3b2e7b113 | B51: kLrLXfgXWp1Hyl6J5OeEt1+ZTOypF4EPMZuB6vFo6XbGcE+RRroc2pI2axmrhUrurT8eGKpkGhGPpW43Wj3lIg== | C51: 45902.544 | D51: CCN Region 2 | E51: Active | G51: Accepting patients | H51: HELFRICH, YOLANDA | I51: No | J51: 1003903873 | K51: Unknown | L51: Dermatology | M51: Dermatology | O51: No | P51: 734-936-8000 | R51: REGENTS OF UNIVERSITY OF MICH | S51: 1500 E MEDICAL CENTER DR | T51: ANN ARBOR | U51: MI | V51: 48109-5000 | W51: REGENTS OF UNIVERSITY OF MICH | X51: 44034.14 | Z51: =_xlfn.XLOOKUP(VALUE(LEFT(V51,5)), 'MI Zip Codes'!A:A, 'MI Zip Codes'!B:B, "County Not Found") -> Washtenaw
A52: 9787f533-5beb-47a4-a5e8-edb4bc6c0bfb | B52: XN9/vmJOtEpTezH7talSZKNY5peZo/yyCb2XzQSxqUeS1wQkKXdYHwKnWxlJ4Ihyw2oYZbRyrUkC9RpZl0nzlg== | C52: 45902.546 | D52: CCN Region 2 | E52: Active | G52: Accepting patients | H52: HELFRICH, YOLANDA | I52: No | J52: 1003903873 | K52: Unknown | L52: Dermatology | M52: Dermatology | P52: 734-936-8000 | Q52: 734-936-9294 | R52: REGENTS OF UNIVERSITY OF MICH | S52: 1500 E MEDICAL CENTER DR | T52: ANN ARBOR | U52: MI | V52: 48109-5000 | W52: REGENTS OF UNIV OF MICH | X52: 43941.04 | Z52: =_xlfn.XLOOKUP(VALUE(LEFT(V52,5)), 'MI Zip Codes'!A:A, 'MI Zip Codes'!B:B, "County Not Found") -> Washtenaw
A53: a3ddbe20-0398-4db9-9d0a-15cc3b00c4b5 | B53: EOJJNgWbEqEgNwYHPd9NOvqoVovEzGkgRikJkXg51PaTCAGSctOk7Rt2QC9A5a5538At8OZXzz47652GEIQhqw== | C53: 45898.756 | D53: CCN Region 2 | E53: Active | G53: Accepting patients | H53: GHAFERI, JESSICA | I53: No | J53: 1003940966 | K53: Unknown | L53: Dermatology - Dermatopathology | M53: Dermatology | P53: 734-712-0655 | Q53: 734-712-0611 | R53: IHA HEALTH SERVICES CORPORATION | S53: 4350 JACKSON RD STE 320 | T53: ANN ARBOR | U53: MI | V53: 48103-1890 | W53: IHA HEALTH SERVICES CORPORATION | X53: 43841.996 | Z53: =_xlfn.XLOOKUP(VALUE(LEFT(V53,5)), 'MI Zip Codes'!A:A, 'MI Zip Codes'!B:B, "County Not Found") -> Washtenaw
A54: db02171d-ff13-4bb0-9d59-2bb77e491dbb | B54: DanFRmFnGfvk77mkAwbWkDoAuIII9dBtF9N6VaTxT/BSjN+2cGw4QUiz1PM9TptT/tTHhEAQx3EfFg7ZMrbhyA== | C54: 45899.654 | D54: CCN Region 2 | E54: Active | G54: Accepting patients | H54: GHAFERI, JESSICA | I54: No | J54: 1003940966 | K54: No | L54: Dermatology | M54: Dermatology | O54: No | P54: 734-712-0655 | Q54: 734-712-0611 | R54: IHA HEALTH SERVICES CORPORATION | S54: 4350 JACKSON RD STE 320 | T54: ANN ARBOR | U54: MI | V54: 48103-1890 | W54: BRIGHTON FAMILY CARE SPECIALISTS | X54: 45048.559 | Z54: =_xlfn.XLOOKUP(VALUE(LEFT(V54,5)), 'MI Zip Codes'!A:A, 'MI Zip Codes'!B:B, "County Not Found") -> Washtenaw
A55: 1e300f6b-c922-412d-b55b-55e82a2f1e84 | B55: RIAN75YkvKLuTXlL0BzsxGfiIPWV4QpTsP+23o15M8iKDhc1pJFw5730Qak5ITogLsIowNJMR0TY2ABVX4nivw== | C55: 45899.922 | D55: CCN Region 2 | E55: Active | F55: No | G55: Accepting patients | H55: GHAFERI, JESSICA | I55: No | J55: 1003940966 | K55: No | L55: Dermatology - Dermatopathology | M55: Dermatology | O55: No | P55: 734-712-0655 | Q55: 734-712-0611 | R55: IHA HEALTH SERVICES CORPORATION | S55: 4350 JACKSON RD STE 320 | T55: ANN ARBOR | U55: MI | V55: 48103-1890 | W55: BRIGHTON FAMILY CARE SPECIALISTS | X55: 45232.932 | Z55: =_xlfn.XLOOKUP(VALUE(LEFT(V55,5)), 'MI Zip Codes'!A:A, 'MI Zip Codes'!B:B, "County Not Found") -> Washtenaw
A56: acd0206a-b306-4de9-9790-5d26d0fd1d12 | B56: eWqwvJHcNF4w9jpImrId9reanJf3x+Nm0ZqkVPcQBxpleyptQGfUJuKTYphlzIYjqgbWbc0JXvZdZK0mdy3ugQ== | C56: 45899.97 | D56: CCN Region 2 | E56: Active | G56: Accepting patients | H56: GHAFERI, JESSICA | I56: No | J56: 1003940966 | K56: No | L56: Dermatology | M56: Dermatology | P56: 734-677-3376 | Q56: 734-572-3229 | R56: IHA INTERNAL MEDICINE DOM | S56: 4200 WHITEHALL DR STE 250 | T56: ANN ARBOR | U56: MI | V56: 48105-9694 | W56: IHA INTERNAL MEDICINE DOM | X56: 43841.996 | Z56: =_xlfn.XLOOKUP(VALUE(LEFT(V56,5)), 'MI Zip Codes'!A:A, 'MI Zip Codes'!B:B, "County Not Found") -> Washtenaw
A57: c587e3dc-b7f5-42ec-a3d3-6f515464d373 | B57: pu6Qq6J2EMgKdaIIBIA2zUz3jnImHrTZmTWCe6cNyuahOp+94bZgiEYhw2q0DzFdZL/Sc75kEWLe517hitjP7w== | C57: 45900.624 | D57: CCN Region 2 | E57: Active | G57: Accepting patients | H57: GHAFERI, JESSICA | I57: No | J57: 1003940966 | K57: No | L57: Pathology - Dermatopathology | M57: Dermatology | O57: No | P57: 734-712-0655 | Q57: 734-712-0611 | R57: IHA HEALTH SERVICES CORPORATION | S57: 4350 JACKSON RD STE 320 | T57: ANN ARBOR | U57: MI | V57: 48103-1890 | W57: BRIGHTON FAMILY CARE SPECIALISTS | X57: 45048.559 | Z57: =_xlfn.XLOOKUP(VALUE(LEFT(V57,5)), 'MI Zip Codes'!A:A, 'MI Zip Codes'!B:B, "County Not Found") -> Washtenaw
A58: 6451d31c-5247-44dc-8fc6-97c7e3eed11f | B58: AuKIy+fmMqIofQ2ENmEa9SetL7P8F/hSlDOU2I73AG2TSd1T5WZo61q4H6R16yxXU7aFBg2rC/Wodl9Kzyt7Wg== | C58: 45900.978 | D58: CCN Region 2 | E58: Active | G58: Accepting patients | H58: GHAFERI, JESSICA | I58: No | J58: 1003940966 | K58: No | L58: Dermatology - Dermatopathology | M58: Dermatology | P58: 734-677-3376 | Q58: 734-572-3229 | R58: IHA INTERNAL MEDICINE DOM | S58: 4200 WHITEHALL DR STE 250 | T58: ANN ARBOR | U58: MI | V58: 48105-9694 | W58: IHA INTERNAL MEDICINE DOM | X58: 43841.996 | Z58: =_xlfn.XLOOKUP(VALUE(LEFT(V58,5)), 'MI Zip Codes'!A:A, 'MI Zip Codes'!B:B, "County Not Found") -> Washtenaw
A59: 152f60e6-3c83-4337-91e7-ab06cf863d56 | B59: tU2aut04cVEUt8YfUbsiYUieY6L35nEgnf5cyJxBx/DTzrpuzlbh0nQS39ZGn5NGXTnqCQQBeove1WpxoBDtMw== | C59: 45901.591 | D59: CCN Region 2 | E59: Active | G59: Accepting patients | H59: GHAFERI, JESSICA | I59: No | J59: 1003940966 | K59: Unknown | L59: Dermatology - Dermatopathology | M59: Dermatology | O59: No | P59: 734-712-0655 | Q59: 734-712-0611 | R59: IHA HEALTH SERVICES CORPORATION | S59: 4350 JACKSON RD STE 320 | T59: ANN ARBOR | U59: MI | V59: 48103-1890 | W59: BRIGHTON FAMILY CARE SPECIALISTS | X59: 45048.559 | Z59: =_xlfn.XLOOKUP(VALUE(LEFT(V59,5)), 'MI Zip Codes'!A:A, 'MI Zip Codes'!B:B, "County Not Found") -> Washtenaw
A60: a24c5da0-0678-4b4b-a091-ab3aabdac857 | B60: cNc+CaX2ZDtNQYSSEXNKU76cfIr7XEbTh7CShoaYDyf0RXtl4PGXTu1mXJJD6Aax8zoQEJIVzajvZ+QmTL4MFA== | C60: 45901.591 | D60: CCN Region 2 | E60: Active | G60: Accepting patients | H60: GHAFERI, JESSICA | I60: No | J60: 1003940966 | K60: Unknown | L60: Dermatology | M60: Dermatology | P60: 734-712-0655 | Q60: 734-712-0611 | R60: IHA HEALTH SERVICES CORPORATION | S60: 4350 JACKSON RD STE 320 | T60: ANN ARBOR | U60: MI | V60: 48103-1890 | W60: IHA HEALTH SERVICES CORPORATION | X60: 43841.996 | Z60: =_xlfn.XLOOKUP(VALUE(LEFT(V60,5)), 'MI Zip Codes'!A:A, 'MI Zip Codes'!B:B, "County Not Found") -> Washtenaw
A61: 5fffec92-86ce-434a-9c31-be7b904b0c14 | B61: fzCSog22LxhJprKH3410qO75QFMRIi6MW25JJswJQrk3A7tJNfLLfMAm3wmwAjqc+AxcciWjalDxj5A+J1lSNA== | C61: 45901.669 | D61: CCN Region 2 | E61: Active | G61: Accepting patients | H61: GHAFERI, JESSICA | I61: No | J61: 1003940966 | K61: No | L61: Pathology - Dermatopathology | M61: Dermatology | P61: 734-677-3376 | Q61: 734-572-3229 | R61: IHA INTERNAL MEDICINE DOM | S61: 4200 WHITEHALL DR STE 250 | T61: ANN ARBOR | U61: MI | V61: 48105-9694 | W61: IHA INTERNAL MEDICINE DOM | X61: 43972.403 | Z61: =_xlfn.XLOOKUP(VALUE(LEFT(V61,5)), 'MI Zip Codes'!A:A, 'MI Zip Codes'!B:B, "County Not Found") -> Washtenaw
A62: 95c8d0e2-4656-49d4-be6c-eba060f6256d | B62: 3wt8N/OpErzNhjyuvnU3Cm16xnfuPefXY2PahGlE/M7IXLsgZFDIs0BuAwkyY7iOeoCCcmknZxAlRrr4m3AsAg== | C62: 45902.542 | D62: CCN Region 2 | E62: Active | G62: Accepting patients | H62: GHAFERI, JESSICA | I62: No | J62: 1003940966 | K62: Unknown | L62: Pathology - Dermatopathology | M62: Dermatology | P62: 734-712-0655 | Q62: 734-712-0611 | R62: IHA HEALTH SERVICES CORPORATION | S62: 4350 JACKSON RD STE 320 | T62: ANN ARBOR | U62: MI | V62: 48103-1890 | W62: IHA HEALTH SERVICES CORPORATION | X62: 43972.403 | Z62: =_xlfn.XLOOKUP(VALUE(LEFT(V62,5)), 'MI Zip Codes'!A:A, 'MI Zip Codes'!B:B, "County Not Found") -> Washtenaw
A63: 7a22d97d-54be-432d-9306-051196719550 | B63: inB1SoenbnF5JuwqiQQffkohJVWXzrU2Azy2emWe5WLG6qjl1M7vAVyTbP07EfnjuGgqyWYloZiXNvzy6V2IRQ== | C63: 46029.711 | D63: CCN Region 2 | E63: Active | G63: Accepting patients | H63: WANG, FRANK | I63: No | J63: 1013114602 | K63: Unknown | L63: Dermatology | M63: Dermatology | O63: No | P63: 734-763-4109 | Q63: 734-936-9294 | R63: REGENTS OF UNIVERSITY OF MICH | S63: 1500 E MEDICAL CENTER DR | T63: ANN ARBOR | U63: MI | V63: 48109-5000 | W63: REGENTS OF UNIVERSITY OF MICH | X63: 43997.255 | Z63: =_xlfn.XLOOKUP(VALUE(LEFT(V63,5)), 'MI Zip Codes'!A:A, 'MI Zip Codes'!B:B, "County Not Found") -> Washtenaw
A64: d884fb27-5136-4a29-915a-505f8bbd11b1 | B64: CoewgOra0DlwhLWgMX15MmhO3VJrH1xa0v0MiwD35ZZ43vorVJ8kRMqlWwMTe7t6qeZZcDt6wV7OUgg5cxAo0g== | C64: 46029.711 | D64: CCN Region 2 | E64: Active | G64: Accepting patients | H64: WANG, FRANK | I64: No | J64: 1013114602 | K64: Unknown | L64: Dermatology | M64: Dermatology | O64: No | P64: 734-763-4109 | R64: REGENTS OF UNIVERSITY OF MICH | S64: 1500 E MEDICAL CENTER DR | T64: ANN ARBOR | U64: MI | V64: 48109-5000 | W64: REGENTS OF UNIVERSITY OF MICH | X64: 44069.158 | Z64: =_xlfn.XLOOKUP(VALUE(LEFT(V64,5)), 'MI Zip Codes'!A:A, 'MI Zip Codes'!B:B, "County Not Found") -> Washtenaw
A65: 4290eb19-d44e-49e6-9cc9-5406461dc2b4 | B65: x0ZlN3YleLMKFNEldL4Yi6/WTFT4F0IP6OTlZWwUyW3W7493NcrW1a1gzkbSmKDo59Wds5VTxJRJuEtH/IZyTg== | C65: 46029.711 | D65: CCN Region 2 | E65: Active | G65: Accepting patients | H65: WANG, FRANK | I65: No | J65: 1013114602 | K65: Unknown | L65: Dermatology | M65: Dermatology | O65: No | P65: 734-936-8000 | R65: REGENTS OF UNIVERSITY OF MICH | S65: 1500 E MEDICAL CENTER DR | T65: ANN ARBOR | U65: MI | V65: 48109-5000 | W65: REGENTS OF UNIV OF MICH | X65: 44478.439 | Z65: =_xlfn.XLOOKUP(VALUE(LEFT(V65,5)), 'MI Zip Codes'!A:A, 'MI Zip Codes'!B:B, "County Not Found") -> Washtenaw
A66: 86a71ebb-3a4b-4edf-a5a7-60438c9a9d0b | B66: V5l2qUcRdhTAo3i3S9NJy25oBZHHTGIaBPsZ+Zmx9KshrdmyYEpy9hwB+dVIvet4BCZLBMVcPASiuyAdnrC1Rw== | C66: 46029.711 | D66: CCN Region 2 | E66: Active | G66: Accepting patients | H66: WANG, FRANK | I66: No | J66: 1013114602 | K66: Unknown | L66: Dermatology | M66: Dermatology | O66: No | P66: 734-936-8000 | R66: REGENTS OF UNIVERSITY OF MICH | S66: 1500 E MEDICAL CENTER DR | T66: ANN ARBOR | U66: MI | V66: 48109-5000 | W66: REGENTS OF UNIVERSITY OF MICH | X66: 44619.085 | Z66: =_xlfn.XLOOKUP(VALUE(LEFT(V66,5)), 'MI Zip Codes'!A:A, 'MI Zip Codes'!B:B, "County Not Found") -> Washtenaw
A67: 1afbd5b2-92cc-43e2-8f85-82af2248a967 | B67: KcLUeSSsW5EtsS7/lIOmeWG+8DwaF5CRjnROZ9Jxsjrq3UKpLFEnzze0HRYABsybcPO9w6Rg27EdZLUeqvzGow== | C67: 46029.711 | D67: CCN Region 2 | E67: Active | G67: Accepting patients | H67: WANG, FRANK | I67: No | J67: 1013114602 | K67: Unknown | L67: Dermatology | M67: Dermatology | O67: No | P67: 734-936-8000 | R67: REGENTS OF UNIVERSITY OF MICH | S67: 1500 E MEDICAL CENTER DR | T67: ANN ARBOR | U67: MI | V67: 48109-5000 | W67: REGENTS OF THE UNIVERSITY OF MICHIGAN | X67: 44493.565 | Z67: =_xlfn.XLOOKUP(VALUE(LEFT(V67,5)), 'MI Zip Codes'!A:A, 'MI Zip Codes'!B:B, "County Not Found") -> Washtenaw
A68: f9821c20-a29f-4daa-8425-9940781e667b | B68: XWrQHI12v9s5m6XIEmTxbxZkUeC5RoLpZmOCD950PQP+M/U79T+Z5tQKJ1++HSF+8ygGkr4FDXF551ekAQLU4w== | C68: 46029.711 | D68: CCN Region 2 | E68: Active | G68: Accepting patients | H68: WANG, FRANK | I68: No | J68: 1013114602 | K68: No | L68: Dermatology | M68: Dermatology | O68: No | P68: 734-763-4109 | R68: REGENTS OF UNIVERSITY OF MICH | S68: 1500 E MEDICAL CENTER DR 8TH FL | T68: ANN ARBOR | U68: MI | V68: 48109-5000 | W68: REGENTS OF UNIVERSITY OF MICH | X68: 44115.976 | Z68: =_xlfn.XLOOKUP(VALUE(LEFT(V68,5)), 'MI Zip Codes'!A:A, 'MI Zip Codes'!B:B, "County Not Found") -> Washtenaw
A69: b70a0ae4-431c-4489-ae2c-ae810dfd265c | B69: jDm68LpYxBlPeUZFfVr4yhFmDVH29+6juNJZtpinyEbKBrMv6fSgklogvLeN+0u/6CVrFM7I59/Oakjn3OuFsg== | C69: 46029.992 | D69: CCN Region 2 | E69: Active | G69: Accepting patients | H69: WANG, FRANK | I69: No | J69: 1013114602 | K69: No | L69: Dermatology | M69: Dermatology | O69: No | P69: 734-998-7400 | R69: REGENTS OF UNIVERSITY OF MICH | S69: 24 FRANK LLOYD WRIGHT DR | T69: ANN ARBOR | U69: MI | V69: 48105-9484 | W69: REGENTS OF UNIVERSITY OF MICH | X69: 44478.439 | Z69: =_xlfn.XLOOKUP(VALUE(LEFT(V69,5)), 'MI Zip Codes'!A:A, 'MI Zip Codes'!B:B, "County Not Found") -> Washtenaw
A70: 6f298d6b-b7d9-4c7c-9dcb-b6a242cec79d | B70: uIKrrHc94Y5hYY+K+BaTG36r2lMCMdaJ0lJLlqOulR+4khbTKcoBNsY+q4jjJWtR4NSKl29AThCn/ihCK7B/zQ== | C70: 46029.711 | D70: CCN Region 2 | E70: Active | G70: Accepting patients | H70: WANG, FRANK | I70: No | J70: 1013114602 | K70: Unknown | L70: Dermatology | M70: Dermatology | O70: No | P70: 734-936-8000 | R70: REGENTS OF UNIVERSITY OF MICH | S70: 1500 E MEDICAL CENTER DR | T70: ANN ARBOR | U70: MI | V70: 48109-5000 | W70: REGENTS OF UNIVERSITY OF MICH | X70: 44479.572 | Z70: =_xlfn.XLOOKUP(VALUE(LEFT(V70,5)), 'MI Zip Codes'!A:A, 'MI Zip Codes'!B:B, "County Not Found") -> Washtenaw
A71: bc510199-847b-49e8-b548-de68e70c696b | B71: HCNaXpLN5u73K1qhhnl4cfls9dYq/hb7LtNBEWC31M3KxeRR5DJxxQBiTvwQEE7AtfI7/hNGHJOJcWeYK0LoGw== | C71: 46029.711 | D71: CCN Region 2 | E71: Active | G71: Accepting patients | H71: WANG, FRANK | I71: No | J71: 1013114602 | K71: Unknown | L71: Dermatology | M71: Dermatology | O71: No | P71: 734-936-8000 | R71: REGENTS OF UNIVERSITY OF MICH | S71: 1500 E MEDICAL CENTER DR | T71: ANN ARBOR | U71: MI | V71: 48109-5000 | W71: REGENTS OF UNIVERSITY OF MICH | X71: 44559.797 | Z71: =_xlfn.XLOOKUP(VALUE(LEFT(V71,5)), 'MI Zip Codes'!A:A, 'MI Zip Codes'!B:B, "County Not Found") -> Washtenaw
A72: 58eade0c-6772-4de0-a4f9-e4be1da6d43d | B72: Obrx5PrDQOGNPIdOXmAPXD5JNE7/JTR8YRdfwMKhRHkf3egC9jFMNl4nvbwiikHZJ0brDT6CtUntAT0JIuzIcg== | C72: 46029.711 | D72: CCN Region 2 | E72: Active | G72: Accepting patients | H72: WANG, FRANK | I72: No | J72: 1013114602 | K72: No | L72: Dermatology | M72: Dermatology | P72: 734-936-4054 | R72: REGENTS OF UNIVERSITY OF MICH | S72: 24 FRANK LLOYD WRIGHT DR # H2350 | T72: ANN ARBOR | U72: MI | V72: 48105-9484 | W72: REGENTS OF THE UNIVERSITY OF MICHIGAN | X72: 43914.983 | Z72: =_xlfn.XLOOKUP(VALUE(LEFT(V72,5)), 'MI Zip Codes'!A:A, 'MI Zip Codes'!B:B, "County Not Found") -> Washtenaw
A73: 57fb4b52-144f-4c66-b6e7-ec351dc1774d | B73: QpBsYqn+PLuI00TDnIQ/biBZJ5yDKjFkOJSe2Ek4I5Ypxt6iUENamfUd2XY6pWM5sVZSGYEjy9vV5Play9A1/Q== | C73: 46029.711 | D73: CCN Region 2 | E73: Active | G73: Accepting patients | H73: WANG, FRANK | I73: No | J73: 1013114602 | K73: Unknown | L73: Dermatology | M73: Dermatology | O73: No | P73: 734-998-7400 | R73: REGENTS OF UNIVERSITY OF MICH | S73: 24 FRANK LLOYD WRIGHT DR | T73: ANN ARBOR | U73: MI | V73: 48105-9484 | W73: REGENTS OF UNIV OF MICH | X73: 44499.878 | Z73: =_xlfn.XLOOKUP(VALUE(LEFT(V73,5)), 'MI Zip Codes'!A:A, 'MI Zip Codes'!B:B, "County Not Found") -> Washtenaw
A74: b02335da-3f7c-4464-9d7a-feec2ff6d620 | B74: YusfJMHk/6CqIwmcOFt+BPZBU9N7Isd1gyHP7d1db2cZrMK+QtKhoM8BJI3Al5d9DCzyK2z7rYQkJqEmoFXuEA== | C74: 45902.629 | D74: CCN Region 2 | E74: Active | F74: No | G74: Accepting patients | H74: IHA OF ANN ARBOR | I74: No | J74: 1013276260 | K74: No | L74: Dermatology | M74: Dermatology | O74: No | P74: 734-477-0200 | R74: IHA OF ANN ARBOR | S74: 2433 OAK VALLEY DR | T74: ANN ARBOR | U74: MI | V74: 48103-7602 | X74: 45219.597 | Z74: =_xlfn.XLOOKUP(VALUE(LEFT(V74,5)), 'MI Zip Codes'!A:A, 'MI Zip Codes'!B:B, "County Not Found") -> Washtenaw
A75: fd5d8c1c-9d61-40a6-977d-045217f3c34e | B75: xtTZ9zLTd8wU+rXTolA2m+GRMbG4TrcmPpezL7qBiYL5Hef6Jhyl/LAqusV60RFwDvqRJNpl5iZVDENfc7hfuA== | C75: 45898.55 | D75: CCN Region 2 | E75: Active | G75: Accepting patients | H75: ORSINI, AMY | I75: No | J75: 1013933431 | K75: Unknown | L75: Dermatology - MOHS-Micrographic Surgery | M75: Dermatology | O75: No | P75: 734-936-8000 | R75: REGENTS OF UNIVERSITY OF MICH | S75: 1500 E MEDICAL CENTER DR | T75: ANN ARBOR | U75: MI | V75: 48109-5000 | W75: REGENTS OF UNIVERSITY OF MICH | X75: 44322.135 | Z75: =_xlfn.XLOOKUP(VALUE(LEFT(V75,5)), 'MI Zip Codes'!A:A, 'MI Zip Codes'!B:B, "County Not Found") -> Washtenaw
A76: b50a1199-6a26-4378-b230-2293eb46e231 | B76: vmixxyjST9bCo+V1SA0H8OoI0E2zFqxj0JXvFKQMFft2NZ6YQ2cynobQOM5lq0i/hsVnA5F/DuxOISOK00zM6g== | C76: 45898.807 | D76: CCN Region 2 | E76: Active | G76: Accepting patients | H76: ORSINI, AMY | I76: No | J76: 1013933431 | K76: Unknown | L76: Dermatology - MOHS-Micrographic Surgery | M76: Dermatology | O76: No | P76: 734-936-8000 | R76: REGENTS OF UNIVERSITY OF MICH | S76: 1500 E MEDICAL CENTER DR | T76: ANN ARBOR | U76: MI | V76: 48109-5000 | W76: REGENTS OF UNIV OF MICH | X76: 44321.112 | Z76: =_xlfn.XLOOKUP(VALUE(LEFT(V76,5)), 'MI Zip Codes'!A:A, 'MI Zip Codes'!B:B, "County Not Found") -> Washtenaw
A77: 516dd1e3-f984-43ed-9877-3607528c3f46 | B77: VO7IDmgrqSw8aS9lvUaD7xwXkmAH1pc3xEmuLahbmfBCinLbxrEFIj1XndRw6TyUZgG9Mdeo524B4GUimdKPsw== | C77: 45899.701 | D77: CCN Region 2 | E77: Active | G77: Accepting patients | H77: ORSINI, AMY | I77: No | J77: 1013933431 | K77: Unknown | L77: Dermatology - Procedural Dermatology | M77: Dermatology | O77: No | P77: 734-936-8000 | R77: REGENTS OF UNIVERSITY OF MICH | S77: 1500 E MEDICAL CENTER DR | T77: ANN ARBOR | U77: MI | V77: 48109-5000 | W77: REGENTS OF UNIVERSITY OF MICH | X77: 44465.524 | Z77: =_xlfn.XLOOKUP(VALUE(LEFT(V77,5)), 'MI Zip Codes'!A:A, 'MI Zip Codes'!B:B, "County Not Found") -> Washtenaw
A78: d69ff12d-0fa4-4c0f-a92b-499e2bcfdbb7 | B78: CSo5YVsEWW6wl5yT9itD+VJVSUQb17FGnHq6sResFjjTqaScgfFGv/Cbxhf8c74pyKEy/9joFgVypDYgwujWKg== | C78: 45899.866 | D78: CCN Region 2 | E78: Active | G78: Accepting patients | H78: ORSINI, AMY | I78: No | J78: 1013933431 | K78: Unknown | L78: Dermatology - Procedural Dermatology | M78: Dermatology | O78: No | P78: 734-936-8000 | R78: REGENTS OF UNIVERSITY OF MICH | S78: 1500 E MEDICAL CENTER DR | T78: ANN ARBOR | U78: MI | V78: 48109-5000 | W78: REGENTS OF UNIVERSITY OF MICH | X78: 44322.136 | Z78: =_xlfn.XLOOKUP(VALUE(LEFT(V78,5)), 'MI Zip Codes'!A:A, 'MI Zip Codes'!B:B, "County Not Found") -> Washtenaw
A79: 2f30ef1d-5bf1-41b2-bc12-49e29ee18bf7 | B79: DOTNJ7GykyEa1VYu+1hM+CI+mD3TeD9grXfnVdgb6mbUqaxpRQygJpKzpDh+x/dKCI0DlbdlA0GRPq1OchRPFw== | C79: 45899.866 | D79: CCN Region 2 | E79: Active | G79: Accepting patients | H79: ORSINI, AMY | I79: No | J79: 1013933431 | K79: Unknown | L79: Dermatology - Procedural Dermatology | M79: Dermatology | O79: No | P79: 734-936-8000 | R79: REGENTS OF UNIVERSITY OF MICH | S79: 1500 E MEDICAL CENTER DR | T79: ANN ARBOR | U79: MI | V79: 48109-5000 | W79: REGENTS OF UNIVERSITY OF MICH | X79: 44619.081 | Z79: =_xlfn.XLOOKUP(VALUE(LEFT(V79,5)), 'MI Zip Codes'!A:A, 'MI Zip Codes'!B:B, "County Not Found") -> Washtenaw
A80: 347e816b-5370-43ca-995b-4be4445c68d1 | B80: VCUubiVMP70kpIhIZOHAaOfnaFn8iIMVXgEQPz8nAAVClGXkeA+hsQMHeF2d8v/cI2p8Yb8ueFEW4wbs89rKTQ== | C80: 45899.867 | D80: CCN Region 2 | E80: Active | G80: Accepting patients | H80: ORSINI, AMY | I80: No | J80: 1013933431 | K80: Unknown | L80: Dermatology | M80: Dermatology | O80: No | P80: 734-936-8000 | Q80: 734-936-9294 | R80: REGENTS OF UNIVERSITY OF MICH | S80: 1500 E MEDICAL CENTER DR | T80: ANN ARBOR | U80: MI | V80: 48109-5000 | W80: REGENTS OF UNIV OF MICH | X80: 44161.977 | Z80: =_xlfn.XLOOKUP(VALUE(LEFT(V80,5)), 'MI Zip Codes'!A:A, 'MI Zip Codes'!B:B, "County Not Found") -> Washtenaw
A81: b67bfb9b-9173-4f6d-b6f6-5115c5dc4695 | B81: IFzPLtnGRF1QSPj1kz+JOQk9Xgr1YfuS6i3x2juTPhf9tV/Dmq8f/kDgXPZOlSKDIKBBCgLg3nyGxTBECBiaTQ== | C81: 45899.88 | D81: CCN Region 2 | E81: Active | G81: Accepting patients | H81: ORSINI, AMY | I81: No | J81: 1013933431 | K81: Unknown | L81: Dermatology - MOHS-Micrographic Surgery | M81: Dermatology | O81: No | P81: 734-936-8000 | R81: REGENTS OF UNIVERSITY OF MICH | S81: 1500 E MEDICAL CENTER DR | T81: ANN ARBOR | U81: MI | V81: 48109-5000 | W81: REGENTS OF THE UNIVERSITY OF MICHIGAN | X81: 44493.568 | Z81: =_xlfn.XLOOKUP(VALUE(LEFT(V81,5)), 'MI Zip Codes'!A:A, 'MI Zip Codes'!B:B, "County Not Found") -> Washtenaw
A82: 33bd5ecf-15b3-4019-a081-528d107c7b71 | B82: EHsMeWUAXbDbZrbE+LUItLH+eoM39WlAOuqmutKATm+HldxYSWHzG1Z7u3YiitT9pPq6d41QMgJYFbuxEyLSqw== | C82: 45899.881 | D82: CCN Region 2 | E82: Active | G82: Accepting patients | H82: ORSINI, AMY | I82: No | J82: 1013933431 | K82: Unknown | L82: Dermatology - Procedural Dermatology | M82: Dermatology | O82: No | P82: 734-936-8000 | R82: REGENTS OF UNIVERSITY OF MICH | S82: 1500 E MEDICAL CENTER DR | T82: ANN ARBOR | U82: MI | V82: 48109-5000 | W82: REGENTS OF THE UNIVERSITY OF MICHIGAN | X82: 44493.568 | Z82: =_xlfn.XLOOKUP(VALUE(LEFT(V82,5)), 'MI Zip Codes'!A:A, 'MI Zip Codes'!B:B, "County Not Found") -> Washtenaw
A83: f513a9d6-538e-4218-a0dd-53c3f3e24d63 | B83: d2SD+XcjctsqaLU6TuAOl6N7PpbJVyKyTNxyNI3zotl9Ycoch8tVUbbLCoLRyc9esBe61WBbDnhEfxdgwf4bYw== | C83: 45899.881 | D83: CCN Region 2 | E83: Active | G83: Accepting patients | H83: ORSINI, AMY | I83: No | J83: 1013933431 | K83: Unknown | L83: Dermatology - Procedural Dermatology | M83: Dermatology | O83: No | P83: 734-936-8000 | R83: REGENTS OF UNIVERSITY OF MICH | S83: 1500 E MEDICAL CENTER DR | T83: ANN ARBOR | U83: MI | V83: 48109-5000 | W83: REGENTS OF THE UNIVERSITY OF MICHIGAN | X83: 44514.636 | Z83: =_xlfn.XLOOKUP(VALUE(LEFT(V83,5)), 'MI Zip Codes'!A:A, 'MI Zip Codes'!B:B, "County Not Found") -> Washtenaw
A84: 22a2c732-0e37-4fea-b542-5633340e031a | B84: DvxY4bDrtGZj+4T7J1JlnU7k3/8WC5A9M8ULwWQ+ls4j6k7cc/cQZCbH38MXWr2bXe7Z0Do7wJknAkjqBP2x8Q== | C84: 45899.922 | D84: CCN Region 2 | E84: Active | G84: Accepting patients | H84: ORSINI, AMY | I84: No | J84: 1013933431 | K84: Unknown | L84: Dermatology - MOHS-Micrographic Surgery | M84: Dermatology | O84: No | P84: 734-936-8000 | R84: REGENTS OF UNIVERSITY OF MICH | S84: 1500 E MEDICAL CENTER DR | T84: ANN ARBOR | U84: MI | V84: 48109-5000 | W84: REGENTS OF THE UNIVERSITY OF MICHIGAN | X84: 44514.636 | Z84: =_xlfn.XLOOKUP(VALUE(LEFT(V84,5)), 'MI Zip Codes'!A:A, 'MI Zip Codes'!B:B, "County Not Found") -> Washtenaw
A85: d80d25be-9bb0-4a1d-acc4-595cb11c9617 | B85: DPZOl3Og2VmbshJSBNgZGVwUK5pwnFn18nkmu73s18IF29QbFILzcaV5321N9fMHzd65UXwuY6zRZ3aI0nLRZA== | C85: 45899.924 | D85: CCN Region 2 | E85: Active | G85: Accepting patients | H85: ORSINI, AMY | I85: No | J85: 1013933431 | K85: Unknown | L85: Dermatology | M85: Dermatology | O85: No | P85: 734-936-8000 | Q85: 734-936-9294 | R85: REGENTS OF UNIVERSITY OF MICH | S85: 1500 E MEDICAL CENTER DR | T85: ANN ARBOR | U85: MI | V85: 48109-5000 | W85: REGENTS OF UNIVERSITY OF MICH | X85: 44151.363 | Z85: =_xlfn.XLOOKUP(VALUE(LEFT(V85,5)), 'MI Zip Codes'!A:A, 'MI Zip Codes'!B:B, "County Not Found") -> Washtenaw
A86: 4eb03b0e-1495-4b6e-ad28-86c69a349566 | B86: nZyYRWhkbTJnV7IGiiGJYZBZPv7crqnAlT2RL14Skes5kcZFAMU4+1c4dCzhAyFszFs4n0msa6k3L9GXlGNtcg== | C86: 45900.764 | D86: CCN Region 2 | E86: Active | G86: Accepting patients | H86: ORSINI, AMY | I86: No | J86: 1013933431 | K86: Unknown | L86: Dermatology | M86: Dermatology | O86: No | P86: 734-936-8000 | R86: REGENTS OF UNIVERSITY OF MICH | S86: 1500 E MEDICAL CENTER DR | T86: ANN ARBOR | U86: MI | V86: 48109-5000 | W86: REGENTS OF THE UNIVERSITY OF MICHIGAN | X86: 44514.636 | Z86: =_xlfn.XLOOKUP(VALUE(LEFT(V86,5)), 'MI Zip Codes'!A:A, 'MI Zip Codes'!B:B, "County Not Found") -> Washtenaw
A87: 1da12ed2-fee0-4a76-9e2e-913c4a99350d | B87: wMvm2lOUUzgVixz0BPyyHA2jG6cAuR4AecTKsqxzceJGchnVNyL/VcvWOMpuJxB6WN4YL/Ff4gd32riy38iSxA== | C87: 45900.828 | D87: CCN Region 2 | E87: Active | G87: Accepting patients | H87: ORSINI, AMY | I87: No | J87: 1013933431 | K87: Unknown | L87: Dermatology | M87: Dermatology | O87: No | P87: 734-936-8000 | R87: REGENTS OF UNIVERSITY OF MICH | S87: 1500 E MEDICAL CENTER DR | T87: ANN ARBOR | U87: MI | V87: 48109-5000 | W87: REGENTS OF UNIVERSITY OF MICH | X87: 44465.524 | Z87: =_xlfn.XLOOKUP(VALUE(LEFT(V87,5)), 'MI Zip Codes'!A:A, 'MI Zip Codes'!B:B, "County Not Found") -> Washtenaw
A88: aaad56a7-0d40-4549-8d57-a8da862e7e5e | B88: K8IbdcLAKQzcEcgxeBEd2v0xuJhZwg8G/ByXsqRlWzGeAOMIj8t8i+KW01M/ZUxWe3Vrzyo+m2vuzetEQMMJpA== | C88: 45901.583 | D88: CCN Region 2 | E88: Active | G88: Accepting patients | H88: ORSINI, AMY | I88: No | J88: 1013933431 | K88: Unknown | L88: Dermatology | M88: Dermatology | O88: No | P88: 734-936-8000 | R88: REGENTS OF UNIVERSITY OF MICH | S88: 1500 E MEDICAL CENTER DR | T88: ANN ARBOR | U88: MI | V88: 48109-5000 | W88: REGENTS OF UNIVERSITY OF MICH | X88: 44619.081 | Z88: =_xlfn.XLOOKUP(VALUE(LEFT(V88,5)), 'MI Zip Codes'!A:A, 'MI Zip Codes'!B:B, "County Not Found") -> Washtenaw
A89: 7e5f7646-0f01-48b1-ad08-c30a70f7378c | B89: YHXyzt3mS4HjaH3GvkocOEMatUGvdDKK9zxQrZiMxOcZ7iZLOgbDLO//6yIDDHCoWJuLIuSlAuMs8jaDPACxtw== | C89: 45901.7 | D89: CCN Region 2 | E89: Active | G89: Accepting patients | H89: ORSINI, AMY | I89: No | J89: 1013933431 | K89: Unknown | L89: Dermatology - MOHS-Micrographic Surgery | M89: Dermatology | O89: No | P89: 734-936-8000 | R89: REGENTS OF UNIVERSITY OF MICH | S89: 1500 E MEDICAL CENTER DR | T89: ANN ARBOR | U89: MI | V89: 48109-5000 | W89: REGENTS OF UNIVERSITY OF MICH | X89: 44619.081 | Z89: =_xlfn.XLOOKUP(VALUE(LEFT(V89,5)), 'MI Zip Codes'!A:A, 'MI Zip Codes'!B:B, "County Not Found") -> Washtenaw
A90: 8c3edab7-72e7-4e1a-94d0-c9be7e489155 | B90: tAG1KUPPsSPzxBoBRYVzcSyt6m7Oei2GKTvCM+fz3NoFqY8TKfphdF+N+cIuB8cl3opbKjcSu1+iLSjbVN+6fQ== | C90: 45901.716 | D90: CCN Region 2 | E90: Active | G90: Accepting patients | H90: ORSINI, AMY | I90: No | J90: 1013933431 | K90: Unknown | L90: Dermatology | M90: Dermatology | O90: No | P90: 734-936-8000 | R90: REGENTS OF UNIVERSITY OF MICH | S90: 1500 E MEDICAL CENTER DR | T90: ANN ARBOR | U90: MI | V90: 48109-5000 | W90: REGENTS OF THE UNIVERSITY OF MICHIGAN | X90: 44493.568 | Z90: =_xlfn.XLOOKUP(VALUE(LEFT(V90,5)), 'MI Zip Codes'!A:A, 'MI Zip Codes'!B:B, "County Not Found") -> Washtenaw
A91: 48f19344-1720-4dd7-b453-cbb2ffe05f3d | B91: OAxfXxMusJbz9H5MUpffGjNVwvFlDzsPowEMD60okFC8Y5uVGN6+B8pkrf/Fl74Ll/lSltBBfuUiEzpAY3LEig== | C91: 45901.72 | D91: CCN Region 2 | E91: Active | G91: Accepting patients | H91: ORSINI, AMY | I91: No | J91: 1013933431 | K91: Unknown | L91: Dermatology - Procedural Dermatology | M91: Dermatology | O91: No | P91: 734-936-8000 | R91: REGENTS OF UNIVERSITY OF MICH | S91: 1500 E MEDICAL CENTER DR | T91: ANN ARBOR | U91: MI | V91: 48109-5000 | W91: REGENTS OF UNIV OF MICH | X91: 44321.112 | Z91: =_xlfn.XLOOKUP(VALUE(LEFT(V91,5)), 'MI Zip Codes'!A:A, 'MI Zip Codes'!B:B, "County Not Found") -> Washtenaw
A92: 2890a379-2476-41be-8eaf-d99656125797 | B92: 1HIpjpDufmnMLjFyu8wLnMa9RKPrmsIKjAEA2XKJrQHD93owAtXrqreETOjxq8VHmJGHMQ/zWG1CgrG6DP68nQ== | C92: 45901.956 | D92: CCN Region 2 | E92: Active | G92: Accepting patients | H92: ORSINI, AMY | I92: No | J92: 1013933431 | K92: Unknown | L92: Dermatology - MOHS-Micrographic Surgery | M92: Dermatology | O92: No | P92: 734-936-8000 | R92: REGENTS OF UNIVERSITY OF MICH | S92: 1500 E MEDICAL CENTER DR | T92: ANN ARBOR | U92: MI | V92: 48109-5000 | W92: REGENTS OF UNIVERSITY OF MICH | X92: 44465.524 | Z92: =_xlfn.XLOOKUP(VALUE(LEFT(V92,5)), 'MI Zip Codes'!A:A, 'MI Zip Codes'!B:B, "County Not Found") -> Washtenaw
A93: 9aa24ef7-2301-4fab-b204-8ac101be0c73 | B93: dSId8P9gonYWLmals/uBvfqaBjF4na8D0SN+mldGPYaF/AJG1YUnb8tS9MWIor92HkHgsRz944p1KGXFLrf5tw== | C93: 45900.766 | D93: CCN Region 2 | E93: Active | F93: No | G93: Accepting patients | H93: ST JOSEPH MERCY HOSPITAL | I93: No | J93: 1023432309 | K93: Unknown | L93: Pathology - Dermatopathology | M93: Dermatology | O93: No | P93: 248-360-5881 | R93: ST JOSEPH MERCY HOSPITAL | S93: 5301 E HURON RIVER DR | T93: ANN ARBOR | U93: MI | V93: 48106 | X93: 45241.192 | Z93: =_xlfn.XLOOKUP(VALUE(LEFT(V93,5)), 'MI Zip Codes'!A:A, 'MI Zip Codes'!B:B, "County Not Found") -> Washtenaw
A94: 57fe9c26-2002-4a53-ba92-15a66af4edb0 | B94: To0stzSvGkJT8xkM4VbX6qmkn86Lr3BCSYd2QsQb1Kg6snbGZvARdhk7w+42MB1esM7T/tMTKJ7LrLZMUhvsKw== | C94: 45898.756 | D94: CCN Region 2 | E94: Active | G94: Accepting patients | H94: PATEL, RAJIV | I94: No | J94: 1033351044 | K94: Unknown | L94: Dermatology - Dermatopathology | M94: Dermatology | P94: 734-936-5738 | R94: REGENTS OF UNIVERSITY OF MICH | S94: 1500 E MEDICAL CENTER DR FL 2 | T94: ANN ARBOR | U94: MI | V94: 48109-5000 | W94: REGENTS OF UNIVERSITY OF MICH | X94: 43915.758 | Z94: =_xlfn.XLOOKUP(VALUE(LEFT(V94,5)), 'MI Zip Codes'!A:A, 'MI Zip Codes'!B:B, "County Not Found") -> Washtenaw
A95: 9054eb42-96ed-4080-b52a-2f2063195bc9 | B95: mwc0uCn5MPUve5cc2q+dcye1Ky1Ll4X730HhnRKVVH09GFEhUZOpCO2npPKHrYLwu/K3RU4eeLJtmexHbA/tWg== | C95: 45899.66 | D95: CCN Region 2 | E95: Active | G95: Accepting patients | H95: PATEL, RAJIV | I95: No | J95: 1033351044 | K95: Unknown | L95: Dermatology - Dermatopathology | M95: Dermatology | O95: No | P95: 734-936-8000 | Q95: 734-936-9294 | R95: REGENTS OF UNIVERSITY OF MICH | S95: 1500 E MEDICAL CENTER DR | T95: ANN ARBOR | U95: MI | V95: 48109-5000 | W95: REGENTS OF UNIVERSITY OF MICH | X95: 44048.235 | Z95: =_xlfn.XLOOKUP(VALUE(LEFT(V95,5)), 'MI Zip Codes'!A:A, 'MI Zip Codes'!B:B, "County Not Found") -> Washtenaw
A96: 1990d5f5-3c70-4a89-b4a3-4532a523f770 | B96: Rdp6+11nx3FYXO+m20fLlNh7DQ8ymvFtCgGGpu0EgVMRI3d3wcO/ZaKqQt7wzcqJorz24VviaHFgUGaimF/UGA== | C96: 45899.82 | D96: CCN Region 2 | E96: Active | G96: Accepting patients | H96: PATEL, RAJIV | I96: No | J96: 1033351044 | K96: Unknown | L96: Dermatology - Dermatopathology | M96: Dermatology | O96: No | P96: 734-936-8000 | R96: REGENTS OF UNIVERSITY OF MICH | S96: 1500 E MEDICAL CENTER DR | T96: ANN ARBOR | U96: MI | V96: 48109-5000 | W96: REGENTS OF UNIVERSITY OF MICH | X96: 44619.09 | Z96: =_xlfn.XLOOKUP(VALUE(LEFT(V96,5)), 'MI Zip Codes'!A:A, 'MI Zip Codes'!B:B, "County Not Found") -> Washtenaw
A97: bbc91739-fde8-44df-a412-50f6d22399ae | B97: +Xw/TZrlbc0vw4E9EZ1VES7N5EUOl8M0jv55L0MlH0M+qf/rXv3aFLfQu8Ic81lQYbFWYCKp/WAhaEEfEB9a0A== | C97: 45899.88 | D97: CCN Region 2 | E97: Active | G97: Accepting patients | H97: PATEL, RAJIV | I97: No | J97: 1033351044 | K97: Unknown | L97: Dermatology - Dermatopathology | M97: Dermatology | O97: No | P97: 734-936-8000 | Q97: 734-936-9294 | R97: REGENTS OF UNIVERSITY OF MICH | S97: 1500 E MEDICAL CENTER DR | T97: ANN ARBOR | U97: MI | V97: 48109-5000 | X97: 44107.978 | Z97: =_xlfn.XLOOKUP(VALUE(LEFT(V97,5)), 'MI Zip Codes'!A:A, 'MI Zip Codes'!B:B, "County Not Found") -> Washtenaw
A98: 08a82b43-5c01-42a3-9fbd-64fe0b055a09 | B98: Pq5j8pTUeQm5aqhxgz5zhRAMm6ZTwZRgLahLz5zWCx3eFg47PFd8uN+UWNX6oUVo4t3BsSGxHbwkufsIcvGjaw== | C98: 45899.973 | D98: CCN Region 2 | E98: Active | G98: Accepting patients | H98: PATEL, RAJIV | I98: No | J98: 1033351044 | K98: Unknown | L98: Dermatology - Dermatopathology | M98: Dermatology | O98: No | P98: 734-936-8000 | Q98: 734-936-9294 | R98: REGENTS OF UNIVERSITY OF MICH | S98: 1500 E MEDICAL CENTER DR | T98: ANN ARBOR | U98: MI | V98: 48109-5000 | W98: REGENTS OF THE UNIVERSITY OF MICHIGAN | X98: 43998.214 | Z98: =_xlfn.XLOOKUP(VALUE(LEFT(V98,5)), 'MI Zip Codes'!A:A, 'MI Zip Codes'!B:B, "County Not Found") -> Washtenaw
A99: 1b7cd788-5654-4601-baaa-700f61063e00 | B99: lVkW5RbEtME+6MyxPiFk/ymkVMpvcGep79Qlr4jJBB9pU2LS5x26pRjkyHyOCrNWagJuA16y9ZKKU4Y9ISKQLw== | C99: 45900.624 | D99: CCN Region 2 | E99: Active | G99: Accepting patients | H99: PATEL, RAJIV | I99: No | J99: 1033351044 | K99: Unknown | L99: Dermatology - Dermatopathology | M99: Dermatology | P99: 734-936-8000 | Q99: 734-936-9294 | R99: REGENTS OF UNIVERSITY OF MICH | S99: 1500 E MEDICAL CENTER DR | T99: ANN ARBOR | U99: MI | V99: 48109-5000 | W99: REGENTS OF UNIV OF MICH | X99: 43941.006 | Z99: =_xlfn.XLOOKUP(VALUE(LEFT(V99,5)), 'MI Zip Codes'!A:A, 'MI Zip Codes'!B:B, "County Not Found") -> Washtenaw
A100: bdf98e1c-be0b-4f93-a5e9-7cc3085e061b | B100: uai9Wvym+39bWoNKZwo27c7by+mktPFOE8lZP8Xvm/smPiV57K2rysGUE88Q4M6fSgkTTH22KfCh+om0dZnB4g== | C100: 45900.65 | D100: CCN Region 2 | E100: Active | G100: Accepting patients | H100: PATEL, RAJIV | I100: No | J100: 1033351044 | K100: Unknown | L100: Dermatology - Dermatopathology | M100: Dermatology | P100: 734-936-5738 | R100: REGENTS OF UNIVERSITY OF MICH | S100: 1500 E MEDICAL CENTER DR FL 2 | T100: ANN ARBOR | U100: MI | V100: 48109-5000 | W100: REGENTS OF THE UNIVERSITY OF MICHIGAN | X100: 43915.082 | Z100: =_xlfn.XLOOKUP(VALUE(LEFT(V100,5)), 'MI Zip Codes'!A:A, 'MI Zip Codes'!B:B, "County Not Found") -> Washtenaw
...

Sheet MI Zip Codes
A1: ZIP Code | B1: County
A2: 48001 | B2: St. Clair
A3: 48002 | B3: St. Clair
A4: 48003 | B4: St. Clair
A5: 48004 | B5: St. Clair
A6: 48005 | B6: Macomb
A7: 48006 | B7: St. Clair
A8: 48007 | B8: Macomb
A9: 48009 | B9: Oakland
A10: 48012 | B10: Oakland
A11: 48014 | B11: Macomb
A12: 48015 | B12: Macomb
A13: 48017 | B13: Macomb
... A1162: 49971 | B1162: Gogebic

Sheet hiddenSheet
A1: ppms_providerservice:ChxXBc3b+Fd0KATrqGxf6awwVSYZI3pupJSuKmstFwrhmyX+U7NlzdtMlVQv5yQ3kLhUq3ujd47Gf5RvmGXVrg==:ppms_providerserviceid=%28Do%20Not%20Modify%29%20Provider%20Service&checksumLogicalName=%28Do%20Not%20Modify%29%20Row%20Checksum&modifiedon=%28Do%20Not%20Modify%29%20Modified%20On&ppms_networknametext=Network%20Name&statuscode=Status&ppms_vss=VSS&ppms_availability=Availability&ppms_providerid=Provider&6bda24be-3f20-4656-ba57-a8aeaaaa4c24.ppms_notesavailable=Notes%20%28Provider%29%20%28Provider%29&ppms_provideridentifer=Provider%20Identifier&ppms_highperformingprovider=HPP&ppms_specialty=Specialty&172b72a4-3029-42fc-b185-2eb5ca00a4bc.ppms_specialtygroup=Specialty%20Group%20%28Specialty%29%20%28Specialty%29&ppms_subservicerollup=Subservice%20Rollup&ppms_telehealthavailable=Telehealth%20Available&ppms_caresitephonenumber=Care%20Site%20Phone%20Number&dd321304-1362-46e3-8699-8688a1353fa1.ppms_caresitefax=Care%20Site%20Fax%20%28Caresite%29%20%28Care%20Site%29&ppms_caresite=Caresite&ppms_caresiteaddress=Care%20Site%20Address&ppms_caresitecity=Care%20Site%20City&ppms_caresitestateprovince=Care%20Site%20State&ppms_caresitezipcode=Care%20Site%20Zip%20Code&ppms_organization=Organization%20%2f%20Group&createdon=Created%20On&ppms_deactivationdate=Deactivation%20Date&ppms_coveragecounty=Coverage%20County
A2: Active | B2: Pending | C2: Inactive | D2: Address Validation Failure | E2: Provider Inactive | F2: Marked for Deletion
A3: No | B3: Yes
A4: Accepting patients | B4: Not accepting new patients | C4: Not taking veterans | D4: Not taking patients for billing reasons | E4: No availability | F4: Asked to be removed from the network
A5: No | B5: Yes
A6: Unknown | B6: Yes | C6: No
A7: No | B7: Yes
